{
   "api_timestamp" : 1569497994,
   "offset" : 0,
   "total" : 38,
   "items" : [
      {
         "disktype" : "SATA",
         "mic" : "NO",
         "state" : "Alive",
         "scheduler_priority" : 0,
         "diskpath" : null,
         "switch" : null,
         "production" : "YES",
         "max_walltime" : 86400,
         "disk_reservation_count" : 3,
         "eth_count" : 1,
         "myri_rate" : 0,
         "next_state" : "UnChanged",
         "host" : "clusterb-1.fakesite.grid5000.fr",
         "chassis" : "Dell Inc. PowerEdge T640 FL1CBX2",
         "nodemodel" : "Dell PowerEdge T640",
         "type" : "default",
         "ib" : "NO",
         "state_num" : 1,
         "api_timestamp" : 1569497994,
         "memcpu" : 65536,
         "gpudevice" : 0,
         "gpu_count" : 4,
         "wattmeter" : "MULTIPLE",
         "last_available_upto" : 0,
         "maintenance" : "NO",
         "cluster_priority" : 201906,
         "links" : [
            {
               "rel" : "member",
               "href" : "//oarapi/resources/nodes/clusterb-1.fakesite.grid5000.fr",
               "title" : "node"
            },
            {
               "href" : "//oarapi/resources/1",
               "rel" : "self"
            },
            {
               "href" : "//oarapi/resources/1/jobs",
               "rel" : "collection",
               "title" : "jobs"
            }
         ],
         "cputype" : "Intel Xeon Silver 4110",
         "disk" : null,
         "next_finaud_decision" : "NO",
         "ib_rate" : 0,
         "gpu_model" : "GeForce RTX 2080 Ti",
         "gpu" : 1,
         "finaud_decision" : "NO",
         "eth_rate" : 10,
         "drain" : "NO",
         "suspended_jobs" : "NO",
         "network_address" : "clusterb-1.fakesite.grid5000.fr",
         "cpuset" : 0,
         "cpucore" : 8,
         "myri_count" : 0,
         "cpufreq" : "2.1",
         "exotic" : "NO",
         "cpu" : 1,
         "last_job_date" : 0,
         "deploy": "YES",
         "ib_count" : 0,
         "expiry_date" : 0,
         "opa_count" : 0,
         "memnode" : 131072,
         "available_upto" : 2147483647,
         "opa_rate" : 0,
         "desktop_computing" : "NO",
         "virtual" : "ivt",
         "id" : 1,
         "cluster" : "clusterb",
         "cpuarch" : "x86_64",
         "ip" : "172.16.64.1",
         "memcore" : 8192,
         "besteffort" : "YES",
         "core" : 1,
         "myri" : "NO"
      },
      {
         "last_available_upto" : 0,
         "wattmeter" : "MULTIPLE",
         "links" : [
            {
               "rel" : "member",
               "href" : "//oarapi/resources/nodes/clusterb-1.fakesite.grid5000.fr",
               "title" : "node"
            },
            {
               "href" : "//oarapi/resources/2",
               "rel" : "self"
            },
            {
               "rel" : "collection",
               "title" : "jobs",
               "href" : "//oarapi/resources/2/jobs"
            }
         ],
         "cluster_priority" : 201906,
         "maintenance" : "NO",
         "memcpu" : 65536,
         "api_timestamp" : 1569497994,
         "gpu_count" : 4,
         "gpudevice" : 0,
         "finaud_decision" : "NO",
         "gpu" : 1,
         "cputype" : "Intel Xeon Silver 4110",
         "disk" : null,
         "next_finaud_decision" : "NO",
         "gpu_model" : "GeForce RTX 2080 Ti",
         "ib_rate" : 0,
         "switch" : null,
         "diskpath" : null,
         "disk_reservation_count" : 3,
         "production" : "YES",
         "max_walltime" : 86400,
         "state" : "Alive",
         "scheduler_priority" : 0,
         "mic" : "NO",
         "disktype" : "SATA",
         "ib" : "NO",
         "type" : "default",
         "state_num" : 1,
         "host" : "clusterb-1.fakesite.grid5000.fr",
         "chassis" : "Dell Inc. PowerEdge T640 FL1CBX2",
         "nodemodel" : "Dell PowerEdge T640",
         "next_state" : "UnChanged",
         "eth_count" : 1,
         "myri_rate" : 0,
         "myri" : "NO",
         "core" : 2,
         "besteffort" : "YES",
         "ib_count" : 0,
         "expiry_date" : 0,
         "cpufreq" : "2.1",
         "exotic" : "NO",
         "myri_count" : 0,
         "deploy": "YES",
         "cpucore" : 8,
         "cpu" : 1,
         "last_job_date" : 0,
         "opa_count" : 0,
         "drain" : "NO",
         "eth_rate" : 10,
         "network_address" : "clusterb-1.fakesite.grid5000.fr",
         "cpuset" : 1,
         "suspended_jobs" : "NO",
         "id" : 2,
         "cluster" : "clusterb",
         "desktop_computing" : "NO",
         "virtual" : "ivt",
         "memcore" : 8192,
         "cpuarch" : "x86_64",
         "ip" : "172.16.64.1",
         "memnode" : 131072,
         "available_upto" : 2147483647,
         "opa_rate" : 0
      },
      {
         "available_upto" : 2147483647,
         "memnode" : 131072,
         "opa_rate" : 0,
         "id" : 3,
         "cluster" : "clusterb",
         "virtual" : "ivt",
         "desktop_computing" : "NO",
         "memcore" : 8192,
         "cpuarch" : "x86_64",
         "ip" : "172.16.64.1",
         "suspended_jobs" : "NO",
         "eth_rate" : 10,
         "drain" : "NO",
         "cpuset" : 2,
         "network_address" : "clusterb-1.fakesite.grid5000.fr",
         "ib_count" : 0,
         "expiry_date" : 0,
         "myri_count" : 0,
         "cpucore" : 8,
         "cpufreq" : "2.1",
         "exotic" : "NO",
         "deploy": "YES",
         "cpu" : 1,
         "last_job_date" : 0,
         "opa_count" : 0,
         "besteffort" : "YES",
         "core" : 3,
         "myri" : "NO",
         "host" : "clusterb-1.fakesite.grid5000.fr",
         "chassis" : "Dell Inc. PowerEdge T640 FL1CBX2",
         "next_state" : "UnChanged",
         "nodemodel" : "Dell PowerEdge T640",
         "myri_rate" : 0,
         "eth_count" : 1,
         "ib" : "NO",
         "type" : "default",
         "state_num" : 1,
         "state" : "Alive",
         "scheduler_priority" : 0,
         "disktype" : "SATA",
         "mic" : "NO",
         "switch" : null,
         "diskpath" : null,
         "disk_reservation_count" : 3,
         "production" : "YES",
         "max_walltime" : 86400,
         "next_finaud_decision" : "NO",
         "disk" : null,
         "cputype" : "Intel Xeon Silver 4110",
         "gpu_model" : "GeForce RTX 2080 Ti",
         "ib_rate" : 0,
         "gpu" : 1,
         "finaud_decision" : "NO",
         "memcpu" : 65536,
         "api_timestamp" : 1569497994,
         "gpu_count" : 4,
         "gpudevice" : 0,
         "last_available_upto" : 0,
         "wattmeter" : "MULTIPLE",
         "links" : [
            {
               "href" : "//oarapi/resources/nodes/clusterb-1.fakesite.grid5000.fr",
               "rel" : "member",
               "title" : "node"
            },
            {
               "rel" : "self",
               "href" : "//oarapi/resources/3"
            },
            {
               "title" : "jobs",
               "rel" : "collection",
               "href" : "//oarapi/resources/3/jobs"
            }
         ],
         "cluster_priority" : 201906,
         "maintenance" : "NO"
      },
      {
         "finaud_decision" : "NO",
         "gpu" : 1,
         "cputype" : "Intel Xeon Silver 4110",
         "disk" : null,
         "next_finaud_decision" : "NO",
         "ib_rate" : 0,
         "gpu_model" : "GeForce RTX 2080 Ti",
         "wattmeter" : "MULTIPLE",
         "last_available_upto" : 0,
         "maintenance" : "NO",
         "cluster_priority" : 201906,
         "links" : [
            {
               "title" : "node",
               "rel" : "member",
               "href" : "//oarapi/resources/nodes/clusterb-1.fakesite.grid5000.fr"
            },
            {
               "rel" : "self",
               "href" : "//oarapi/resources/4"
            },
            {
               "title" : "jobs",
               "rel" : "collection",
               "href" : "//oarapi/resources/4/jobs"
            }
         ],
         "api_timestamp" : 1569497994,
         "memcpu" : 65536,
         "gpudevice" : 0,
         "gpu_count" : 4,
         "type" : "default",
         "ib" : "NO",
         "state_num" : 1,
         "myri_rate" : 0,
         "eth_count" : 1,
         "next_state" : "UnChanged",
         "host" : "clusterb-1.fakesite.grid5000.fr",
         "chassis" : "Dell Inc. PowerEdge T640 FL1CBX2",
         "nodemodel" : "Dell PowerEdge T640",
         "diskpath" : null,
         "switch" : null,
         "production" : "YES",
         "max_walltime" : 86400,
         "disk_reservation_count" : 3,
         "disktype" : "SATA",
         "mic" : "NO",
         "scheduler_priority" : 0,
         "state" : "Alive",
         "myri" : "NO",
         "core" : 4,
         "besteffort" : "YES",
         "desktop_computing" : "NO",
         "virtual" : "ivt",
         "id" : 4,
         "cluster" : "clusterb",
         "cpuarch" : "x86_64",
         "ip" : "172.16.64.1",
         "memcore" : 8192,
         "memnode" : 131072,
         "available_upto" : 2147483647,
         "opa_rate" : 0,
         "cpucore" : 8,
         "myri_count" : 0,
         "cpufreq" : "2.1",
         "exotic" : "NO",
         "deploy": "YES",
         "cpu" : 1,
         "last_job_date" : 0,
         "expiry_date" : 0,
         "ib_count" : 0,
         "opa_count" : 0,
         "drain" : "NO",
         "eth_rate" : 10,
         "suspended_jobs" : "NO",
         "cpuset" : 3,
         "network_address" : "clusterb-1.fakesite.grid5000.fr"
      },
      {
         "gpu_model" : "GeForce RTX 2080 Ti",
         "ib_rate" : 0,
         "disk" : null,
         "next_finaud_decision" : "NO",
         "cputype" : "Intel Xeon Silver 4110",
         "gpu" : 2,
         "finaud_decision" : "NO",
         "gpudevice" : 1,
         "gpu_count" : 4,
         "api_timestamp" : 1569497994,
         "memcpu" : 65536,
         "maintenance" : "NO",
         "links" : [
            {
               "rel" : "member",
               "href" : "//oarapi/resources/nodes/clusterb-1.fakesite.grid5000.fr",
               "title" : "node"
            },
            {
               "rel" : "self",
               "href" : "//oarapi/resources/5"
            },
            {
               "rel" : "collection",
               "title" : "jobs",
               "href" : "//oarapi/resources/5/jobs"
            }
         ],
         "cluster_priority" : 201906,
         "wattmeter" : "MULTIPLE",
         "last_available_upto" : 0,
         "myri_rate" : 0,
         "eth_count" : 1,
         "next_state" : "UnChanged",
         "nodemodel" : "Dell PowerEdge T640",
         "host" : "clusterb-1.fakesite.grid5000.fr",
         "chassis" : "Dell Inc. PowerEdge T640 FL1CBX2",
         "state_num" : 1,
         "type" : "default",
         "ib" : "NO",
         "disktype" : "SATA",
         "mic" : "NO",
         "state" : "Alive",
         "scheduler_priority" : 0,
         "production" : "YES",
         "max_walltime" : 86400,
         "disk_reservation_count" : 3,
         "diskpath" : null,
         "switch" : null,
         "besteffort" : "YES",
         "core" : 5,
         "myri" : "NO",
         "opa_rate" : 0,
         "available_upto" : 2147483647,
         "memnode" : 131072,
         "ip" : "172.16.64.1",
         "cpuarch" : "x86_64",
         "memcore" : 8192,
         "virtual" : "ivt",
         "desktop_computing" : "NO",
         "id" : 5,
         "cluster" : "clusterb",
         "eth_rate" : 10,
         "network_address" : "clusterb-1.fakesite.grid5000.fr",
         "drain" : "NO",
         "suspended_jobs" : "NO",
         "cpuset" : 4,
         "opa_count" : 0,
         "cpucore" : 8,
         "myri_count" : 0,
         "cpufreq" : "2.1",
         "exotic" : "NO",
         "deploy": "YES",
         "cpu" : 1,
         "last_job_date" : 0,
         "ib_count" : 0,
         "expiry_date" : 0
      },
      {
         "next_state" : "UnChanged",
         "host" : "clusterb-1.fakesite.grid5000.fr",
         "chassis" : "Dell Inc. PowerEdge T640 FL1CBX2",
         "nodemodel" : "Dell PowerEdge T640",
         "eth_count" : 1,
         "myri_rate" : 0,
         "state_num" : 1,
         "ib" : "NO",
         "type" : "default",
         "scheduler_priority" : 0,
         "state" : "Alive",
         "disktype" : "SATA",
         "mic" : "NO",
         "disk_reservation_count" : 3,
         "production" : "YES",
         "max_walltime" : 86400,
         "switch" : null,
         "diskpath" : null,
         "ib_rate" : 0,
         "gpu_model" : "GeForce RTX 2080 Ti",
         "disk" : null,
         "cputype" : "Intel Xeon Silver 4110",
         "next_finaud_decision" : "NO",
         "finaud_decision" : "NO",
         "gpu" : 2,
         "gpu_count" : 4,
         "gpudevice" : 1,
         "memcpu" : 65536,
         "api_timestamp" : 1569497994,
         "cluster_priority" : 201906,
         "links" : [
            {
               "rel" : "member",
               "href" : "//oarapi/resources/nodes/clusterb-1.fakesite.grid5000.fr",
               "title" : "node"
            },
            {
               "rel" : "self",
               "href" : "//oarapi/resources/6"
            },
            {
               "title" : "jobs",
               "rel" : "collection",
               "href" : "//oarapi/resources/6/jobs"
            }
         ],
         "maintenance" : "NO",
         "last_available_upto" : 0,
         "wattmeter" : "MULTIPLE",
         "opa_rate" : 0,
         "memnode" : 131072,
         "available_upto" : 2147483647,
         "memcore" : 8192,
         "cpuarch" : "x86_64",
         "ip" : "172.16.64.1",
         "id" : 6,
         "cluster" : "clusterb",
         "desktop_computing" : "NO",
         "virtual" : "ivt",
         "eth_rate" : 10,
         "network_address" : "clusterb-1.fakesite.grid5000.fr",
         "drain" : "NO",
         "suspended_jobs" : "NO",
         "cpuset" : 5,
         "opa_count" : 0,
         "ib_count" : 0,
         "expiry_date" : 0,
         "myri_count" : 0,
         "cpufreq" : "2.1",
         "exotic" : "NO",
         "cpucore" : 8,
         "cpu" : 1,
         "deploy": "YES",
         "last_job_date" : 0,
         "besteffort" : "YES",
         "core" : 6,
         "myri" : "NO"
      },
      {
         "opa_rate" : 0,
         "memnode" : 131072,
         "available_upto" : 2147483647,
         "cpuarch" : "x86_64",
         "ip" : "172.16.64.1",
         "memcore" : 8192,
         "virtual" : "ivt",
         "desktop_computing" : "NO",
         "cluster" : "clusterb",
         "id" : 7,
         "drain" : "NO",
         "eth_rate" : 10,
         "network_address" : "clusterb-1.fakesite.grid5000.fr",
         "cpuset" : 6,
         "suspended_jobs" : "NO",
         "opa_count" : 0,
         "myri_count" : 0,
         "cpucore" : 8,
         "cpufreq" : "2.1",
         "exotic" : "NO",
         "cpu" : 1,
         "deploy": "YES",
         "last_job_date" : 0,
         "expiry_date" : 0,
         "ib_count" : 0,
         "besteffort" : "YES",
         "myri" : "NO",
         "core" : 7,
         "myri_rate" : 0,
         "eth_count" : 1,
         "host" : "clusterb-1.fakesite.grid5000.fr",
         "chassis" : "Dell Inc. PowerEdge T640 FL1CBX2",
         "next_state" : "UnChanged",
         "nodemodel" : "Dell PowerEdge T640",
         "state_num" : 1,
         "type" : "default",
         "ib" : "NO",
         "mic" : "NO",
         "disktype" : "SATA",
         "scheduler_priority" : 0,
         "state" : "Alive",
         "max_walltime" : 86400,
         "production" : "YES",
         "disk_reservation_count" : 3,
         "diskpath" : null,
         "switch" : null,
         "ib_rate" : 0,
         "gpu_model" : "GeForce RTX 2080 Ti",
         "disk" : null,
         "cputype" : "Intel Xeon Silver 4110",
         "next_finaud_decision" : "NO",
         "gpu" : 2,
         "finaud_decision" : "NO",
         "gpudevice" : 1,
         "gpu_count" : 4,
         "api_timestamp" : 1569497994,
         "memcpu" : 65536,
         "maintenance" : "NO",
         "links" : [
            {
               "href" : "//oarapi/resources/nodes/clusterb-1.fakesite.grid5000.fr",
               "rel" : "member",
               "title" : "node"
            },
            {
               "href" : "//oarapi/resources/7",
               "rel" : "self"
            },
            {
               "rel" : "collection",
               "href" : "//oarapi/resources/7/jobs",
               "title" : "jobs"
            }
         ],
         "cluster_priority" : 201906,
         "wattmeter" : "MULTIPLE",
         "last_available_upto" : 0
      },
      {
         "state_num" : 1,
         "type" : "default",
         "ib" : "NO",
         "myri_rate" : 0,
         "eth_count" : 1,
         "nodemodel" : "Dell PowerEdge T640",
         "host" : "clusterb-1.fakesite.grid5000.fr",
         "chassis" : "Dell Inc. PowerEdge T640 FL1CBX2",
         "next_state" : "UnChanged",
         "production" : "YES",
         "max_walltime" : 86400,
         "disk_reservation_count" : 3,
         "diskpath" : null,
         "switch" : null,
         "disktype" : "SATA",
         "mic" : "NO",
         "state" : "Alive",
         "scheduler_priority" : 0,
         "gpu" : 2,
         "finaud_decision" : "NO",
         "gpu_model" : "GeForce RTX 2080 Ti",
         "ib_rate" : 0,
         "disk" : null,
         "cputype" : "Intel Xeon Silver 4110",
         "next_finaud_decision" : "NO",
         "maintenance" : "NO",
         "links" : [
            {
               "rel" : "member",
               "title" : "node",
               "href" : "//oarapi/resources/nodes/clusterb-1.fakesite.grid5000.fr"
            },
            {
               "href" : "//oarapi/resources/8",
               "rel" : "self"
            },
            {
               "href" : "//oarapi/resources/8/jobs",
               "rel" : "collection",
               "title" : "jobs"
            }
         ],
         "cluster_priority" : 201906,
         "wattmeter" : "MULTIPLE",
         "last_available_upto" : 0,
         "gpudevice" : 1,
         "gpu_count" : 4,
         "api_timestamp" : 1569497994,
         "memcpu" : 65536,
         "cpuarch" : "x86_64",
         "ip" : "172.16.64.1",
         "memcore" : 8192,
         "virtual" : "ivt",
         "desktop_computing" : "NO",
         "cluster" : "clusterb",
         "id" : 8,
         "opa_rate" : 0,
         "memnode" : 131072,
         "available_upto" : 2147483647,
         "opa_count" : 0,
         "cpufreq" : "2.1",
         "exotic" : "NO",
         "myri_count" : 0,
         "last_job_date" : 0,
         "cpucore" : 8,
         "cpu" : 1,
         "deploy": "YES",
         "ib_count" : 0,
         "expiry_date" : 0,
         "drain" : "NO",
         "eth_rate" : 10,
         "suspended_jobs" : "NO",
         "cpuset" : 7,
         "network_address" : "clusterb-1.fakesite.grid5000.fr",
         "core" : 8,
         "myri" : "NO",
         "besteffort" : "YES"
      },
      {
         "besteffort" : "YES",
         "myri" : "NO",
         "core" : 9,
         "drain" : "NO",
         "eth_rate" : 10,
         "suspended_jobs" : "NO",
         "network_address" : "clusterb-1.fakesite.grid5000.fr",
         "cpuset" : 8,
         "opa_count" : 0,
         "cpu" : 2,
         "myri_count" : 0,
         "cpufreq" : "2.1",
         "exotic" : "NO",
         "cpucore" : 8,
         "last_job_date" : 0,
         "deploy": "YES",
         "ib_count" : 0,
         "expiry_date" : 0,
         "opa_rate" : 0,
         "available_upto" : 2147483647,
         "memnode" : 131072,
         "cpuarch" : "x86_64",
         "ip" : "172.16.64.1",
         "memcore" : 8192,
         "virtual" : "ivt",
         "desktop_computing" : "NO",
         "cluster" : "clusterb",
         "id" : 9,
         "gpudevice" : 2,
         "gpu_count" : 4,
         "api_timestamp" : 1569497994,
         "memcpu" : 65536,
         "maintenance" : "NO",
         "links" : [
            {
               "rel" : "member",
               "href" : "//oarapi/resources/nodes/clusterb-1.fakesite.grid5000.fr",
               "title" : "node"
            },
            {
               "href" : "//oarapi/resources/9",
               "rel" : "self"
            },
            {
               "title" : "jobs",
               "rel" : "collection",
               "href" : "//oarapi/resources/9/jobs"
            }
         ],
         "cluster_priority" : 201906,
         "wattmeter" : "MULTIPLE",
         "last_available_upto" : 0,
         "gpu_model" : "GeForce RTX 2080 Ti",
         "ib_rate" : 0,
         "disk" : null,
         "next_finaud_decision" : "NO",
         "cputype" : "Intel Xeon Silver 4110",
         "gpu" : 3,
         "finaud_decision" : "NO",
         "disktype" : "SATA",
         "mic" : "NO",
         "state" : "Alive",
         "scheduler_priority" : 0,
         "max_walltime" : 86400,
         "production" : "YES",
         "disk_reservation_count" : 3,
         "diskpath" : null,
         "switch" : null,
         "myri_rate" : 0,
         "eth_count" : 1,
         "host" : "clusterb-1.fakesite.grid5000.fr",
         "chassis" : "Dell Inc. PowerEdge T640 FL1CBX2",
         "next_state" : "UnChanged",
         "nodemodel" : "Dell PowerEdge T640",
         "state_num" : 1,
         "type" : "default",
         "ib" : "NO"
      },
      {
         "ib_rate" : 0,
         "gpu_model" : "GeForce RTX 2080 Ti",
         "cputype" : "Intel Xeon Silver 4110",
         "disk" : null,
         "next_finaud_decision" : "NO",
         "finaud_decision" : "NO",
         "gpu" : 3,
         "gpudevice" : 2,
         "gpu_count" : 4,
         "api_timestamp" : 1569497994,
         "memcpu" : 65536,
         "maintenance" : "NO",
         "cluster_priority" : 201906,
         "links" : [
            {
               "rel" : "member",
               "title" : "node",
               "href" : "//oarapi/resources/nodes/clusterb-1.fakesite.grid5000.fr"
            },
            {
               "href" : "//oarapi/resources/10",
               "rel" : "self"
            },
            {
               "href" : "//oarapi/resources/10/jobs",
               "rel" : "collection",
               "title" : "jobs"
            }
         ],
         "wattmeter" : "MULTIPLE",
         "last_available_upto" : 0,
         "myri_rate" : 0,
         "eth_count" : 1,
         "host" : "clusterb-1.fakesite.grid5000.fr",
         "chassis" : "Dell Inc. PowerEdge T640 FL1CBX2",
         "next_state" : "UnChanged",
         "nodemodel" : "Dell PowerEdge T640",
         "state_num" : 1,
         "type" : "default",
         "ib" : "NO",
         "mic" : "NO",
         "disktype" : "SATA",
         "state" : "Alive",
         "scheduler_priority" : 0,
         "production" : "YES",
         "max_walltime" : 86400,
         "disk_reservation_count" : 3,
         "diskpath" : null,
         "switch" : null,
         "besteffort" : "YES",
         "myri" : "NO",
         "core" : 10,
         "opa_rate" : 0,
         "memnode" : 131072,
         "available_upto" : 2147483647,
         "cpuarch" : "x86_64",
         "ip" : "172.16.64.1",
         "memcore" : 8192,
         "virtual" : "ivt",
         "desktop_computing" : "NO",
         "cluster" : "clusterb",
         "id" : 10,
         "eth_rate" : 10,
         "suspended_jobs" : "NO",
         "drain" : "NO",
         "cpuset" : 9,
         "network_address" : "clusterb-1.fakesite.grid5000.fr",
         "opa_count" : 0,
         "myri_count" : 0,
         "cpu" : 2,
         "cpufreq" : "2.1",
         "exotic" : "NO",
         "cpucore" : 8,
         "last_job_date" : 0,
         "deploy": "YES",
         "ib_count" : 0,
         "expiry_date" : 0
      },
      {
         "switch" : null,
         "diskpath" : null,
         "disk_reservation_count" : 3,
         "production" : "YES",
         "max_walltime" : 86400,
         "state" : "Alive",
         "scheduler_priority" : 0,
         "disktype" : "SATA",
         "mic" : "NO",
         "ib" : "NO",
         "type" : "default",
         "state_num" : 1,
         "next_state" : "UnChanged",
         "nodemodel" : "Dell PowerEdge T640",
         "host" : "clusterb-1.fakesite.grid5000.fr",
         "chassis" : "Dell Inc. PowerEdge T640 FL1CBX2",
         "eth_count" : 1,
         "myri_rate" : 0,
         "last_available_upto" : 0,
         "wattmeter" : "MULTIPLE",
         "cluster_priority" : 201906,
         "links" : [
            {
               "title" : "node",
               "rel" : "member",
               "href" : "//oarapi/resources/nodes/clusterb-1.fakesite.grid5000.fr"
            },
            {
               "rel" : "self",
               "href" : "//oarapi/resources/11"
            },
            {
               "rel" : "collection",
               "title" : "jobs",
               "href" : "//oarapi/resources/11/jobs"
            }
         ],
         "maintenance" : "NO",
         "memcpu" : 65536,
         "api_timestamp" : 1569497994,
         "gpu_count" : 4,
         "gpudevice" : 2,
         "finaud_decision" : "NO",
         "gpu" : 3,
         "disk" : null,
         "cputype" : "Intel Xeon Silver 4110",
         "next_finaud_decision" : "NO",
         "gpu_model" : "GeForce RTX 2080 Ti",
         "ib_rate" : 0,
         "ib_count" : 0,
         "expiry_date" : 0,
         "myri_count" : 0,
         "cpucore" : 8,
         "cpufreq" : "2.1",
         "exotic" : "NO",
         "deploy": "YES",
         "cpu" : 2,
         "last_job_date" : 0,
         "opa_count" : 0,
         "drain" : "NO",
         "eth_rate" : 10,
         "suspended_jobs" : "NO",
         "cpuset" : 10,
         "network_address" : "clusterb-1.fakesite.grid5000.fr",
         "id" : 11,
         "cluster" : "clusterb",
         "virtual" : "ivt",
         "desktop_computing" : "NO",
         "memcore" : 8192,
         "cpuarch" : "x86_64",
         "ip" : "172.16.64.1",
         "available_upto" : 2147483647,
         "memnode" : 131072,
         "opa_rate" : 0,
         "myri" : "NO",
         "core" : 11,
         "besteffort" : "YES"
      },
      {
         "mic" : "NO",
         "disktype" : "SATA",
         "scheduler_priority" : 0,
         "state" : "Alive",
         "max_walltime" : 86400,
         "production" : "YES",
         "disk_reservation_count" : 3,
         "diskpath" : null,
         "switch" : null,
         "eth_count" : 1,
         "myri_rate" : 0,
         "host" : "clusterb-1.fakesite.grid5000.fr",
         "chassis" : "Dell Inc. PowerEdge T640 FL1CBX2",
         "next_state" : "UnChanged",
         "nodemodel" : "Dell PowerEdge T640",
         "state_num" : 1,
         "type" : "default",
         "ib" : "NO",
         "gpudevice" : 2,
         "gpu_count" : 4,
         "api_timestamp" : 1569497994,
         "memcpu" : 65536,
         "maintenance" : "NO",
         "cluster_priority" : 201906,
         "links" : [
            {
               "title" : "node",
               "rel" : "member",
               "href" : "//oarapi/resources/nodes/clusterb-1.fakesite.grid5000.fr"
            },
            {
               "href" : "//oarapi/resources/12",
               "rel" : "self"
            },
            {
               "title" : "jobs",
               "rel" : "collection",
               "href" : "//oarapi/resources/12/jobs"
            }
         ],
         "wattmeter" : "MULTIPLE",
         "last_available_upto" : 0,
         "gpu_model" : "GeForce RTX 2080 Ti",
         "ib_rate" : 0,
         "disk" : null,
         "next_finaud_decision" : "NO",
         "cputype" : "Intel Xeon Silver 4110",
         "gpu" : 3,
         "finaud_decision" : "NO",
         "cpuset" : 11,
         "eth_rate" : 10,
         "drain" : "NO",
         "network_address" : "clusterb-1.fakesite.grid5000.fr",
         "suspended_jobs" : "NO",
         "opa_count" : 0,
         "myri_count" : 0,
         "cpufreq" : "2.1",
         "exotic" : "NO",
         "cpu" : 2,
         "cpucore" : 8,
         "last_job_date" : 0,
         "deploy": "YES",
         "expiry_date" : 0,
         "ib_count" : 0,
         "opa_rate" : 0,
         "memnode" : 131072,
         "available_upto" : 2147483647,
         "ip" : "172.16.64.1",
         "cpuarch" : "x86_64",
         "memcore" : 8192,
         "virtual" : "ivt",
         "desktop_computing" : "NO",
         "cluster" : "clusterb",
         "id" : 12,
         "besteffort" : "YES",
         "core" : 12,
         "myri" : "NO"
      },
      {
         "state_num" : 1,
         "type" : "default",
         "ib" : "NO",
         "myri_rate" : 0,
         "eth_count" : 1,
         "next_state" : "UnChanged",
         "host" : "clusterb-1.fakesite.grid5000.fr",
         "chassis" : "Dell Inc. PowerEdge T640 FL1CBX2",
         "nodemodel" : "Dell PowerEdge T640",
         "max_walltime" : 86400,
         "production" : "YES",
         "disk_reservation_count" : 3,
         "diskpath" : null,
         "switch" : null,
         "mic" : "NO",
         "disktype" : "SATA",
         "state" : "Alive",
         "scheduler_priority" : 0,
         "finaud_decision" : "NO",
         "gpu" : 4,
         "ib_rate" : 0,
         "gpu_model" : "GeForce RTX 2080 Ti",
         "next_finaud_decision" : "NO",
         "disk" : null,
         "cputype" : "Intel Xeon Silver 4110",
         "maintenance" : "NO",
         "links" : [
            {
               "href" : "//oarapi/resources/nodes/clusterb-1.fakesite.grid5000.fr",
               "rel" : "member",
               "title" : "node"
            },
            {
               "rel" : "self",
               "href" : "//oarapi/resources/13"
            },
            {
               "title" : "jobs",
               "rel" : "collection",
               "href" : "//oarapi/resources/13/jobs"
            }
         ],
         "cluster_priority" : 201906,
         "wattmeter" : "MULTIPLE",
         "last_available_upto" : 0,
         "gpudevice" : 3,
         "gpu_count" : 4,
         "api_timestamp" : 1569497994,
         "memcpu" : 65536,
         "cpuarch" : "x86_64",
         "ip" : "172.16.64.1",
         "memcore" : 8192,
         "virtual" : "ivt",
         "desktop_computing" : "NO",
         "cluster" : "clusterb",
         "id" : 13,
         "opa_rate" : 0,
         "available_upto" : 2147483647,
         "memnode" : 131072,
         "opa_count" : 0,
         "myri_count" : 0,
         "cpu" : 2,
         "cpufreq" : "2.1",
         "exotic" : "NO",
         "cpucore" : 8,
         "deploy": "YES",
         "last_job_date" : 0,
         "expiry_date" : 0,
         "ib_count" : 0,
         "cpuset" : 12,
         "eth_rate" : 10,
         "drain" : "NO",
         "suspended_jobs" : "NO",
         "network_address" : "clusterb-1.fakesite.grid5000.fr",
         "myri" : "NO",
         "core" : 13,
         "besteffort" : "YES"
      },
      {
         "finaud_decision" : "NO",
         "gpu" : 4,
         "gpu_model" : "GeForce RTX 2080 Ti",
         "ib_rate" : 0,
         "cputype" : "Intel Xeon Silver 4110",
         "disk" : null,
         "next_finaud_decision" : "NO",
         "links" : [
            {
               "rel" : "member",
               "title" : "node",
               "href" : "//oarapi/resources/nodes/clusterb-1.fakesite.grid5000.fr"
            },
            {
               "rel" : "self",
               "href" : "//oarapi/resources/14"
            },
            {
               "href" : "//oarapi/resources/14/jobs",
               "rel" : "collection",
               "title" : "jobs"
            }
         ],
         "cluster_priority" : 201906,
         "maintenance" : "NO",
         "last_available_upto" : 0,
         "wattmeter" : "MULTIPLE",
         "gpu_count" : 4,
         "gpudevice" : 3,
         "memcpu" : 65536,
         "api_timestamp" : 1569497994,
         "state_num" : 1,
         "ib" : "NO",
         "type" : "default",
         "nodemodel" : "Dell PowerEdge T640",
         "next_state" : "UnChanged",
         "host" : "clusterb-1.fakesite.grid5000.fr",
         "chassis" : "Dell Inc. PowerEdge T640 FL1CBX2",
         "eth_count" : 1,
         "myri_rate" : 0,
         "disk_reservation_count" : 3,
         "production" : "YES",
         "max_walltime" : 86400,
         "switch" : null,
         "diskpath" : null,
         "scheduler_priority" : 0,
         "state" : "Alive",
         "disktype" : "SATA",
         "mic" : "NO",
         "core" : 14,
         "myri" : "NO",
         "besteffort" : "YES",
         "memcore" : 8192,
         "cpuarch" : "x86_64",
         "ip" : "172.16.64.1",
         "cluster" : "clusterb",
         "id" : 14,
         "virtual" : "ivt",
         "desktop_computing" : "NO",
         "opa_rate" : 0,
         "memnode" : 131072,
         "available_upto" : 2147483647,
         "opa_count" : 0,
         "ib_count" : 0,
         "expiry_date" : 0,
         "myri_count" : 0,
         "cpufreq" : "2.1",
         "exotic" : "NO",
         "cpu" : 2,
         "cpucore" : 8,
         "deploy": "YES",
         "last_job_date" : 0,
         "suspended_jobs" : "NO",
         "eth_rate" : 10,
         "drain" : "NO",
         "network_address" : "clusterb-1.fakesite.grid5000.fr",
         "cpuset" : 13
      },
      {
         "core" : 15,
         "myri" : "NO",
         "besteffort" : "YES",
         "opa_count" : 0,
         "ib_count" : 0,
         "expiry_date" : 0,
         "myri_count" : 0,
         "cpucore" : 8,
         "cpufreq" : "2.1",
         "exotic" : "NO",
         "deploy": "YES",
         "cpu" : 2,
         "last_job_date" : 0,
         "eth_rate" : 10,
         "network_address" : "clusterb-1.fakesite.grid5000.fr",
         "drain" : "NO",
         "suspended_jobs" : "NO",
         "cpuset" : 14,
         "memcore" : 8192,
         "cpuarch" : "x86_64",
         "ip" : "172.16.64.1",
         "id" : 15,
         "cluster" : "clusterb",
         "desktop_computing" : "NO",
         "virtual" : "ivt",
         "opa_rate" : 0,
         "memnode" : 131072,
         "available_upto" : 2147483647,
         "cluster_priority" : 201906,
         "links" : [
            {
               "rel" : "member",
               "title" : "node",
               "href" : "//oarapi/resources/nodes/clusterb-1.fakesite.grid5000.fr"
            },
            {
               "href" : "//oarapi/resources/15",
               "rel" : "self"
            },
            {
               "rel" : "collection",
               "title" : "jobs",
               "href" : "//oarapi/resources/15/jobs"
            }
         ],
         "maintenance" : "NO",
         "last_available_upto" : 0,
         "wattmeter" : "MULTIPLE",
         "gpu_count" : 4,
         "gpudevice" : 3,
         "memcpu" : 65536,
         "api_timestamp" : 1569497994,
         "gpu" : 4,
         "finaud_decision" : "NO",
         "gpu_model" : "GeForce RTX 2080 Ti",
         "ib_rate" : 0,
         "disk" : null,
         "next_finaud_decision" : "NO",
         "cputype" : "Intel Xeon Silver 4110",
         "disk_reservation_count" : 3,
         "max_walltime" : 86400,
         "production" : "YES",
         "switch" : null,
         "diskpath" : null,
         "state" : "Alive",
         "scheduler_priority" : 0,
         "disktype" : "SATA",
         "mic" : "NO",
         "state_num" : 1,
         "ib" : "NO",
         "type" : "default",
         "nodemodel" : "Dell PowerEdge T640",
         "next_state" : "UnChanged",
         "host" : "clusterb-1.fakesite.grid5000.fr",
         "chassis" : "Dell Inc. PowerEdge T640 FL1CBX2",
         "myri_rate" : 0,
         "eth_count" : 1
      },
      {
         "myri" : "NO",
         "core" : 16,
         "besteffort" : "YES",
         "memcore" : 8192,
         "cpuarch" : "x86_64",
         "ip" : "172.16.64.1",
         "cluster" : "clusterb",
         "id" : 16,
         "virtual" : "ivt",
         "desktop_computing" : "NO",
         "opa_rate" : 0,
         "memnode" : 131072,
         "available_upto" : 2147483647,
         "opa_count" : 0,
         "ib_count" : 0,
         "expiry_date" : 0,
         "cpufreq" : "2.1",
         "exotic" : "NO",
         "myri_count" : 0,
         "cpucore" : 8,
         "cpu" : 2,
         "last_job_date" : 0,
         "deploy": "YES",
         "suspended_jobs" : "NO",
         "eth_rate" : 10,
         "drain" : "NO",
         "network_address" : "clusterb-1.fakesite.grid5000.fr",
         "cpuset" : 15,
         "gpu" : 4,
         "finaud_decision" : "NO",
         "ib_rate" : 0,
         "gpu_model" : "GeForce RTX 2080 Ti",
         "next_finaud_decision" : "NO",
         "disk" : null,
         "cputype" : "Intel Xeon Silver 4110",
         "cluster_priority" : 201906,
         "links" : [
            {
               "rel" : "member",
               "href" : "//oarapi/resources/nodes/clusterb-1.fakesite.grid5000.fr",
               "title" : "node"
            },
            {
               "rel" : "self",
               "href" : "//oarapi/resources/16"
            },
            {
               "title" : "jobs",
               "rel" : "collection",
               "href" : "//oarapi/resources/16/jobs"
            }
         ],
         "maintenance" : "NO",
         "last_available_upto" : 0,
         "wattmeter" : "MULTIPLE",
         "gpu_count" : 4,
         "gpudevice" : 3,
         "memcpu" : 65536,
         "api_timestamp" : 1569497994,
         "state_num" : 1,
         "ib" : "NO",
         "type" : "default",
         "next_state" : "UnChanged",
         "nodemodel" : "Dell PowerEdge T640",
         "host" : "clusterb-1.fakesite.grid5000.fr",
         "chassis" : "Dell Inc. PowerEdge T640 FL1CBX2",
         "myri_rate" : 0,
         "eth_count" : 1,
         "disk_reservation_count" : 3,
         "max_walltime" : 86400,
         "production" : "YES",
         "switch" : null,
         "diskpath" : null,
         "scheduler_priority" : 0,
         "state" : "Alive",
         "disktype" : "SATA",
         "mic" : "NO"
      },
      {
         "core" : null,
         "myri" : "NO",
         "besteffort" : "YES",
         "myri_count" : 0,
         "cpu" : null,
         "cpufreq" : "2.1",
         "cpucore" : 8,
         "deploy" : "YES",
         "last_job_date" : 0,
         "expiry_date" : 0,
         "ib_count" : 0,
         "opa_count" : 0,
         "drain" : "NO",
         "eth_rate" : 10,
         "cpuset" : -1,
         "network_address" : "",
         "suspended_jobs" : "NO",
         "virtual" : "ivt",
         "desktop_computing" : "NO",
         "cluster" : "clusterb",
         "id" : 17,
         "cpuarch" : "x86_64",
         "ip" : "172.16.64.1",
         "memcore" : 8192,
         "memnode" : 131072,
         "available_upto" : 0,
         "opa_rate" : 0,
         "wattmeter" : "MULTIPLE",
         "last_available_upto" : 0,
         "maintenance" : "NO",
         "links" : [
            {
               "href" : "//oarapi/resources/nodes/",
               "rel" : "member",
               "title" : "node"
            },
            {
               "rel" : "self",
               "href" : "//oarapi/resources/17"
            },
            {
               "href" : "//oarapi/resources/17/jobs",
               "rel" : "collection",
               "title" : "jobs"
            }
         ],
         "cluster_priority" : 201906,
         "api_timestamp" : 1569497994,
         "memcpu" : 65536,
         "gpudevice" : null,
         "gpu_count" : 4,
         "finaud_decision" : "NO",
         "gpu" : null,
         "next_finaud_decision" : "NO",
         "disk" : "sdb.clusterb-1",
         "cputype" : "Intel Xeon Silver 4110",
         "gpu_model" : null,
         "ib_rate" : 0,
         "diskpath" : "/dev/disk/by-path/pci-0000:02:00.0-scsi-0:0:1:0",
         "switch" : null,
         "max_walltime" : 0,
         "production" : "YES",
         "disk_reservation_count" : 3,
         "disktype" : "SATA",
         "mic" : "NO",
         "state" : "Alive",
         "scheduler_priority" : 0,
         "type" : "disk",
         "ib" : "NO",
         "exotic" : "NO",
         "state_num" : 1,
         "myri_rate" : 0,
         "eth_count" : 1,
         "nodemodel" : "Dell PowerEdge T640",
         "next_state" : "UnChanged",
         "host" : "clusterb-1.fakesite.grid5000.fr",
         "chassis" : "Dell Inc. PowerEdge T640 FL1CBX2"
      },
      {
         "ib_rate" : 0,
         "gpu_model" : null,
         "disk" : "sdc.clusterb-1",
         "cputype" : "Intel Xeon Silver 4110",
         "next_finaud_decision" : "NO",
         "gpu" : null,
         "finaud_decision" : "NO",
         "gpu_count" : 4,
         "gpudevice" : null,
         "memcpu" : 65536,
         "api_timestamp" : 1569497994,
         "cluster_priority" : 201906,
         "links" : [
            {
               "rel" : "member",
               "title" : "node",
               "href" : "//oarapi/resources/nodes/"
            },
            {
               "rel" : "self",
               "href" : "//oarapi/resources/18"
            },
            {
               "title" : "jobs",
               "rel" : "collection",
               "href" : "//oarapi/resources/18/jobs"
            }
         ],
         "maintenance" : "NO",
         "last_available_upto" : 0,
         "wattmeter" : "MULTIPLE",
         "nodemodel" : "Dell PowerEdge T640",
         "next_state" : "UnChanged",
         "host" : "clusterb-1.fakesite.grid5000.fr",
         "chassis" : "Dell Inc. PowerEdge T640 FL1CBX2",
         "eth_count" : 1,
         "myri_rate" : 0,
         "state_num" : 1,
         "ib" : "NO",
         "exotic" : "NO",
         "type" : "disk",
         "state" : "Alive",
         "scheduler_priority" : 0,
         "mic" : "NO",
         "disktype" : "SATA",
         "disk_reservation_count" : 3,
         "max_walltime" : 0,
         "production" : "YES",
         "switch" : null,
         "diskpath" : "/dev/disk/by-path/pci-0000:02:00.0-scsi-0:0:2:0",
         "besteffort" : "YES",
         "myri" : "NO",
         "core" : null,
         "opa_rate" : 0,
         "memnode" : 131072,
         "available_upto" : 0,
         "memcore" : 8192,
         "cpuarch" : "x86_64",
         "ip" : "172.16.64.1",
         "cluster" : "clusterb",
         "id" : 18,
         "virtual" : "ivt",
         "desktop_computing" : "NO",
         "eth_rate" : 10,
         "cpuset" : -1,
         "drain" : "NO",
         "network_address" : "",
         "suspended_jobs" : "NO",
         "opa_count" : 0,
         "ib_count" : 0,
         "expiry_date" : 0,
         "cpufreq" : "2.1",
         "myri_count" : 0,
         "cpucore" : 8,
         "cpu" : null,
         "deploy" : "YES",
         "last_job_date" : 0
      },
      {
         "eth_rate" : 10,
         "drain" : "NO",
         "network_address" : "",
         "suspended_jobs" : "NO",
         "cpuset" : -1,
         "last_job_date" : 0,
         "myri_count" : 0,
         "cpufreq" : "2.1",
         "cpucore" : 8,
         "cpu" : null,
         "deploy" : "YES",
         "expiry_date" : 0,
         "ib_count" : 0,
         "opa_count" : 0,
         "memnode" : 131072,
         "available_upto" : 0,
         "opa_rate" : 0,
         "virtual" : "ivt",
         "desktop_computing" : "NO",
         "cluster" : "clusterb",
         "id" : 19,
         "cpuarch" : "x86_64",
         "ip" : "172.16.64.1",
         "memcore" : 8192,
         "besteffort" : "YES",
         "myri" : "NO",
         "core" : null,
         "disktype" : "SATA",
         "mic" : "NO",
         "scheduler_priority" : 0,
         "state" : "Alive",
         "diskpath" : "/dev/disk/by-path/pci-0000:02:00.0-scsi-0:0:3:0",
         "switch" : null,
         "max_walltime" : 0,
         "production" : "YES",
         "disk_reservation_count" : 3,
         "eth_count" : 1,
         "myri_rate" : 0,
         "nodemodel" : "Dell PowerEdge T640",
         "next_state" : "UnChanged",
         "host" : "clusterb-1.fakesite.grid5000.fr",
         "chassis" : "Dell Inc. PowerEdge T640 FL1CBX2",
         "type" : "disk",
         "ib" : "NO",
         "exotic" : "NO",
         "state_num" : 1,
         "api_timestamp" : 1569497994,
         "memcpu" : 65536,
         "gpudevice" : null,
         "gpu_count" : 4,
         "wattmeter" : "MULTIPLE",
         "last_available_upto" : 0,
         "maintenance" : "NO",
         "links" : [
            {
               "rel" : "member",
               "title" : "node",
               "href" : "//oarapi/resources/nodes/"
            },
            {
               "href" : "//oarapi/resources/19",
               "rel" : "self"
            },
            {
               "rel" : "collection",
               "href" : "//oarapi/resources/19/jobs",
               "title" : "jobs"
            }
         ],
         "cluster_priority" : 201906,
         "cputype" : "Intel Xeon Silver 4110",
         "disk" : "sdd.clusterb-1",
         "next_finaud_decision" : "NO",
         "ib_rate" : 0,
         "gpu_model" : null,
         "finaud_decision" : "NO",
         "gpu" : null
      },
      {
         "besteffort" : "YES",
         "core" : 17,
         "myri" : "NO",
         "eth_rate" : 10,
         "drain" : "NO",
         "suspended_jobs" : "NO",
         "network_address" : "clusterb-2.fakesite.grid5000.fr",
         "cpuset" : 0,
         "myri_count" : 0,
         "cpucore" : 8,
         "cpufreq" : "2.1",
         "last_job_date" : 0,
         "cpu" : 3,
         "deploy": "YES",
         "ib_count" : 0,
         "expiry_date" : 0,
         "opa_count" : 0,
         "memnode" : 131072,
         "available_upto" : 2147483647,
         "opa_rate" : 0,
         "desktop_computing" : "NO",
         "virtual" : "ivt",
         "cluster" : "clusterb",
         "id" : 20,
         "cpuarch" : "x86_64",
         "ip" : "172.16.64.2",
         "memcore" : 8192,
         "api_timestamp" : 1569497994,
         "memcpu" : 65536,
         "gpudevice" : 0,
         "gpu_count" : 4,
         "wattmeter" : "MULTIPLE",
         "last_available_upto" : 0,
         "maintenance" : "NO",
         "links" : [
            {
               "href" : "//oarapi/resources/nodes/clusterb-2.fakesite.grid5000.fr",
               "rel" : "member",
               "title" : "node"
            },
            {
               "href" : "//oarapi/resources/20",
               "rel" : "self"
            },
            {
               "rel" : "collection",
               "href" : "//oarapi/resources/20/jobs",
               "title" : "jobs"
            }
         ],
         "cluster_priority" : 201906,
         "disk" : null,
         "next_finaud_decision" : "NO",
         "cputype" : "Intel Xeon Silver 4110",
         "gpu_model" : "GeForce RTX 2080 Ti",
         "ib_rate" : 0,
         "gpu" : 5,
         "finaud_decision" : "NO",
         "disktype" : "SATA",
         "mic" : "NO",
         "state" : "Alive",
         "scheduler_priority" : 0,
         "diskpath" : null,
         "switch" : null,
         "max_walltime" : 86400,
         "production" : "YES",
         "disk_reservation_count" : 3,
         "myri_rate" : 0,
         "eth_count" : 1,
         "nodemodel" : "Dell PowerEdge T640",
         "next_state" : "UnChanged",
         "host" : "clusterb-2.fakesite.grid5000.fr",
         "chassis" : "Dell Inc. PowerEdge T640 9L1CBX2",
         "type" : "default",
         "ib" : "NO",
         "state_num" : 1
      },
      {
         "besteffort" : "YES",
         "core" : 18,
         "myri" : "NO",
         "suspended_jobs" : "NO",
         "eth_rate" : 10,
         "drain" : "NO",
         "network_address" : "clusterb-2.fakesite.grid5000.fr",
         "cpuset" : 1,
         "opa_count" : 0,
         "myri_count" : 0,
         "cpufreq" : "2.1",
         "exotic" : "NO",
         "cpucore" : 8,
         "cpu" : 3,
         "last_job_date" : 0,
         "deploy": "YES",
         "expiry_date" : 0,
         "ib_count" : 0,
         "opa_rate" : 0,
         "available_upto" : 2147483647,
         "memnode" : 131072,
         "cpuarch" : "x86_64",
         "ip" : "172.16.64.2",
         "memcore" : 8192,
         "virtual" : "ivt",
         "desktop_computing" : "NO",
         "id" : 21,
         "cluster" : "clusterb",
         "gpudevice" : 0,
         "gpu_count" : 4,
         "api_timestamp" : 1569497994,
         "memcpu" : 65536,
         "maintenance" : "NO",
         "cluster_priority" : 201906,
         "links" : [
            {
               "rel" : "member",
               "title" : "node",
               "href" : "//oarapi/resources/nodes/clusterb-2.fakesite.grid5000.fr"
            },
            {
               "href" : "//oarapi/resources/21",
               "rel" : "self"
            },
            {
               "href" : "//oarapi/resources/21/jobs",
               "rel" : "collection",
               "title" : "jobs"
            }
         ],
         "wattmeter" : "MULTIPLE",
         "last_available_upto" : 0,
         "gpu_model" : "GeForce RTX 2080 Ti",
         "ib_rate" : 0,
         "disk" : null,
         "cputype" : "Intel Xeon Silver 4110",
         "next_finaud_decision" : "NO",
         "finaud_decision" : "NO",
         "gpu" : 5,
         "mic" : "NO",
         "disktype" : "SATA",
         "scheduler_priority" : 0,
         "state" : "Alive",
         "max_walltime" : 86400,
         "production" : "YES",
         "disk_reservation_count" : 3,
         "diskpath" : null,
         "switch" : null,
         "eth_count" : 1,
         "myri_rate" : 0,
         "next_state" : "UnChanged",
         "nodemodel" : "Dell PowerEdge T640",
         "host" : "clusterb-2.fakesite.grid5000.fr",
         "chassis" : "Dell Inc. PowerEdge T640 9L1CBX2",
         "state_num" : 1,
         "type" : "default",
         "ib" : "NO"
      },
      {
         "myri" : "NO",
         "core" : 19,
         "besteffort" : "YES",
         "ip" : "172.16.64.2",
         "cpuarch" : "x86_64",
         "memcore" : 8192,
         "virtual" : "ivt",
         "desktop_computing" : "NO",
         "cluster" : "clusterb",
         "id" : 22,
         "opa_rate" : 0,
         "available_upto" : 2147483647,
         "memnode" : 131072,
         "opa_count" : 0,
         "myri_count" : 0,
         "cpucore" : 8,
         "cpufreq" : "2.1",
         "exotic" : "NO",
         "last_job_date" : 0,
         "cpu" : 3,
         "deploy": "YES",
         "expiry_date" : 0,
         "ib_count" : 0,
         "eth_rate" : 10,
         "network_address" : "clusterb-2.fakesite.grid5000.fr",
         "drain" : "NO",
         "suspended_jobs" : "NO",
         "cpuset" : 2,
         "gpu" : 5,
         "finaud_decision" : "NO",
         "ib_rate" : 0,
         "gpu_model" : "GeForce RTX 2080 Ti",
         "disk" : null,
         "next_finaud_decision" : "NO",
         "cputype" : "Intel Xeon Silver 4110",
         "maintenance" : "NO",
         "links" : [
            {
               "href" : "//oarapi/resources/nodes/clusterb-2.fakesite.grid5000.fr",
               "rel" : "member",
               "title" : "node"
            },
            {
               "href" : "//oarapi/resources/22",
               "rel" : "self"
            },
            {
               "href" : "//oarapi/resources/22/jobs",
               "rel" : "collection",
               "title" : "jobs"
            }
         ],
         "cluster_priority" : 201906,
         "wattmeter" : "MULTIPLE",
         "last_available_upto" : 0,
         "gpudevice" : 0,
         "gpu_count" : 4,
         "api_timestamp" : 1569497994,
         "memcpu" : 65536,
         "state_num" : 1,
         "type" : "default",
         "ib" : "NO",
         "eth_count" : 1,
         "myri_rate" : 0,
         "next_state" : "UnChanged",
         "nodemodel" : "Dell PowerEdge T640",
         "host" : "clusterb-2.fakesite.grid5000.fr",
         "chassis" : "Dell Inc. PowerEdge T640 9L1CBX2",
         "max_walltime" : 86400,
         "production" : "YES",
         "disk_reservation_count" : 3,
         "diskpath" : null,
         "switch" : null,
         "mic" : "NO",
         "disktype" : "SATA",
         "state" : "Alive",
         "scheduler_priority" : 0
      },
      {
         "diskpath" : null,
         "switch" : null,
         "max_walltime" : 86400,
         "production" : "YES",
         "disk_reservation_count" : 3,
         "mic" : "NO",
         "disktype" : "SATA",
         "scheduler_priority" : 0,
         "state" : "Alive",
         "type" : "default",
         "ib" : "NO",
         "state_num" : 1,
         "myri_rate" : 0,
         "eth_count" : 1,
         "nodemodel" : "Dell PowerEdge T640",
         "next_state" : "UnChanged",
         "host" : "clusterb-2.fakesite.grid5000.fr",
         "chassis" : "Dell Inc. PowerEdge T640 9L1CBX2",
         "wattmeter" : "MULTIPLE",
         "last_available_upto" : 0,
         "maintenance" : "NO",
         "cluster_priority" : 201906,
         "links" : [
            {
               "href" : "//oarapi/resources/nodes/clusterb-2.fakesite.grid5000.fr",
               "rel" : "member",
               "title" : "node"
            },
            {
               "href" : "//oarapi/resources/23",
               "rel" : "self"
            },
            {
               "title" : "jobs",
               "rel" : "collection",
               "href" : "//oarapi/resources/23/jobs"
            }
         ],
         "api_timestamp" : 1569497994,
         "memcpu" : 65536,
         "gpudevice" : 0,
         "gpu_count" : 4,
         "finaud_decision" : "NO",
         "gpu" : 5,
         "disk" : null,
         "next_finaud_decision" : "NO",
         "cputype" : "Intel Xeon Silver 4110",
         "ib_rate" : 0,
         "gpu_model" : "GeForce RTX 2080 Ti",
         "myri_count" : 0,
         "cpucore" : 8,
         "cpufreq" : "2.1",
         "exotic" : "NO",
         "cpu" : 3,
         "deploy": "YES",
         "last_job_date" : 0,
         "ib_count" : 0,
         "expiry_date" : 0,
         "opa_count" : 0,
         "eth_rate" : 10,
         "drain" : "NO",
         "suspended_jobs" : "NO",
         "cpuset" : 3,
         "network_address" : "clusterb-2.fakesite.grid5000.fr",
         "virtual" : "ivt",
         "desktop_computing" : "NO",
         "cluster" : "clusterb",
         "id" : 23,
         "cpuarch" : "x86_64",
         "ip" : "172.16.64.2",
         "memcore" : 8192,
         "memnode" : 131072,
         "available_upto" : 2147483647,
         "opa_rate" : 0,
         "core" : 20,
         "myri" : "NO",
         "besteffort" : "YES"
      },
      {
         "wattmeter" : "MULTIPLE",
         "last_available_upto" : 0,
         "maintenance" : "NO",
         "links" : [
            {
               "rel" : "member",
               "href" : "//oarapi/resources/nodes/clusterb-2.fakesite.grid5000.fr",
               "title" : "node"
            },
            {
               "href" : "//oarapi/resources/24",
               "rel" : "self"
            },
            {
               "href" : "//oarapi/resources/24/jobs",
               "rel" : "collection",
               "title" : "jobs"
            }
         ],
         "cluster_priority" : 201906,
         "api_timestamp" : 1569497994,
         "memcpu" : 65536,
         "gpudevice" : 1,
         "gpu_count" : 4,
         "gpu" : 6,
         "finaud_decision" : "NO",
         "next_finaud_decision" : "NO",
         "disk" : null,
         "cputype" : "Intel Xeon Silver 4110",
         "gpu_model" : "GeForce RTX 2080 Ti",
         "ib_rate" : 0,
         "diskpath" : null,
         "switch" : null,
         "max_walltime" : 86400,
         "production" : "YES",
         "disk_reservation_count" : 3,
         "disktype" : "SATA",
         "mic" : "NO",
         "scheduler_priority" : 0,
         "state" : "Alive",
         "type" : "default",
         "ib" : "NO",
         "state_num" : 1,
         "myri_rate" : 0,
         "eth_count" : 1,
         "host" : "clusterb-2.fakesite.grid5000.fr",
         "chassis" : "Dell Inc. PowerEdge T640 9L1CBX2",
         "nodemodel" : "Dell PowerEdge T640",
         "next_state" : "UnChanged",
         "core" : 21,
         "myri" : "NO",
         "besteffort" : "YES",
         "last_job_date" : 0,
         "myri_count" : 0,
         "cpufreq" : "2.1",
         "exotic" : "NO",
         "cpucore" : 8,
         "cpu" : 3,
         "deploy": "YES",
         "expiry_date" : 0,
         "ib_count" : 0,
         "opa_count" : 0,
         "drain" : "NO",
         "eth_rate" : 10,
         "network_address" : "clusterb-2.fakesite.grid5000.fr",
         "suspended_jobs" : "NO",
         "cpuset" : 4,
         "virtual" : "ivt",
         "desktop_computing" : "NO",
         "cluster" : "clusterb",
         "id" : 24,
         "cpuarch" : "x86_64",
         "ip" : "172.16.64.2",
         "memcore" : 8192,
         "available_upto" : 2147483647,
         "memnode" : 131072,
         "opa_rate" : 0
      },
      {
         "myri_rate" : 0,
         "eth_count" : 1,
         "next_state" : "UnChanged",
         "nodemodel" : "Dell PowerEdge T640",
         "host" : "clusterb-2.fakesite.grid5000.fr",
         "chassis" : "Dell Inc. PowerEdge T640 9L1CBX2",
         "type" : "default",
         "ib" : "NO",
         "state_num" : 1,
         "disktype" : "SATA",
         "mic" : "NO",
         "scheduler_priority" : 0,
         "state" : "Alive",
         "diskpath" : null,
         "switch" : null,
         "production" : "YES",
         "max_walltime" : 86400,
         "disk_reservation_count" : 3,
         "cputype" : "Intel Xeon Silver 4110",
         "disk" : null,
         "next_finaud_decision" : "NO",
         "ib_rate" : 0,
         "gpu_model" : "GeForce RTX 2080 Ti",
         "finaud_decision" : "NO",
         "gpu" : 6,
         "api_timestamp" : 1569497994,
         "memcpu" : 65536,
         "gpudevice" : 1,
         "gpu_count" : 4,
         "wattmeter" : "MULTIPLE",
         "last_available_upto" : 0,
         "maintenance" : "NO",
         "links" : [
            {
               "rel" : "member",
               "href" : "//oarapi/resources/nodes/clusterb-2.fakesite.grid5000.fr",
               "title" : "node"
            },
            {
               "href" : "//oarapi/resources/25",
               "rel" : "self"
            },
            {
               "rel" : "collection",
               "title" : "jobs",
               "href" : "//oarapi/resources/25/jobs"
            }
         ],
         "cluster_priority" : 201906,
         "available_upto" : 2147483647,
         "memnode" : 131072,
         "opa_rate" : 0,
         "virtual" : "ivt",
         "desktop_computing" : "NO",
         "cluster" : "clusterb",
         "id" : 25,
         "cpuarch" : "x86_64",
         "ip" : "172.16.64.2",
         "memcore" : 8192,
         "drain" : "NO",
         "eth_rate" : 10,
         "suspended_jobs" : "NO",
         "network_address" : "clusterb-2.fakesite.grid5000.fr",
         "cpuset" : 5,
         "myri_count" : 0,
         "cpufreq" : "2.1",
         "exotic" : "NO",
         "cpucore" : 8,
         "cpu" : 3,
         "deploy": "YES",
         "last_job_date" : 0,
         "expiry_date" : 0,
         "ib_count" : 0,
         "opa_count" : 0,
         "besteffort" : "YES",
         "core" : 22,
         "myri" : "NO"
      },
      {
         "besteffort" : "YES",
         "core" : 23,
         "myri" : "NO",
         "memnode" : 131072,
         "available_upto" : 2147483647,
         "opa_rate" : 0,
         "cluster" : "clusterb",
         "id" : 26,
         "virtual" : "ivt",
         "desktop_computing" : "NO",
         "memcore" : 8192,
         "cpuarch" : "x86_64",
         "ip" : "172.16.64.2",
         "eth_rate" : 10,
         "drain" : "NO",
         "network_address" : "clusterb-2.fakesite.grid5000.fr",
         "suspended_jobs" : "NO",
         "cpuset" : 6,
         "ib_count" : 0,
         "expiry_date" : 0,
         "myri_count" : 0,
         "cpucore" : 8,
         "cpufreq" : "2.1",
         "exotic" : "NO",
         "last_job_date" : 0,
         "cpu" : 3,
         "deploy": "YES",
         "opa_count" : 0,
         "disk" : null,
         "cputype" : "Intel Xeon Silver 4110",
         "next_finaud_decision" : "NO",
         "gpu_model" : "GeForce RTX 2080 Ti",
         "ib_rate" : 0,
         "gpu" : 6,
         "finaud_decision" : "NO",
         "memcpu" : 65536,
         "api_timestamp" : 1569497994,
         "gpu_count" : 4,
         "gpudevice" : 1,
         "last_available_upto" : 0,
         "wattmeter" : "MULTIPLE",
         "links" : [
            {
               "rel" : "member",
               "href" : "//oarapi/resources/nodes/clusterb-2.fakesite.grid5000.fr",
               "title" : "node"
            },
            {
               "href" : "//oarapi/resources/26",
               "rel" : "self"
            },
            {
               "rel" : "collection",
               "title" : "jobs",
               "href" : "//oarapi/resources/26/jobs"
            }
         ],
         "cluster_priority" : 201906,
         "maintenance" : "NO",
         "next_state" : "UnChanged",
         "nodemodel" : "Dell PowerEdge T640",
         "host" : "clusterb-2.fakesite.grid5000.fr",
         "chassis" : "Dell Inc. PowerEdge T640 9L1CBX2",
         "myri_rate" : 0,
         "eth_count" : 1,
         "ib" : "NO",
         "type" : "default",
         "state_num" : 1,
         "scheduler_priority" : 0,
         "state" : "Alive",
         "disktype" : "SATA",
         "mic" : "NO",
         "switch" : null,
         "diskpath" : null,
         "disk_reservation_count" : 3,
         "production" : "YES",
         "max_walltime" : 86400
      },
      {
         "gpu" : 6,
         "finaud_decision" : "NO",
         "ib_rate" : 0,
         "gpu_model" : "GeForce RTX 2080 Ti",
         "disk" : null,
         "cputype" : "Intel Xeon Silver 4110",
         "next_finaud_decision" : "NO",
         "links" : [
            {
               "title" : "node",
               "rel" : "member",
               "href" : "//oarapi/resources/nodes/clusterb-2.fakesite.grid5000.fr"
            },
            {
               "rel" : "self",
               "href" : "//oarapi/resources/27"
            },
            {
               "title" : "jobs",
               "rel" : "collection",
               "href" : "//oarapi/resources/27/jobs"
            }
         ],
         "cluster_priority" : 201906,
         "maintenance" : "NO",
         "last_available_upto" : 0,
         "wattmeter" : "MULTIPLE",
         "gpu_count" : 4,
         "gpudevice" : 1,
         "memcpu" : 65536,
         "api_timestamp" : 1569497994,
         "state_num" : 1,
         "ib" : "NO",
         "type" : "default",
         "host" : "clusterb-2.fakesite.grid5000.fr",
         "chassis" : "Dell Inc. PowerEdge T640 9L1CBX2",
         "next_state" : "UnChanged",
         "nodemodel" : "Dell PowerEdge T640",
         "eth_count" : 1,
         "myri_rate" : 0,
         "disk_reservation_count" : 3,
         "production" : "YES",
         "max_walltime" : 86400,
         "switch" : null,
         "diskpath" : null,
         "scheduler_priority" : 0,
         "state" : "Alive",
         "disktype" : "SATA",
         "mic" : "NO",
         "myri" : "NO",
         "core" : 24,
         "besteffort" : "YES",
         "memcore" : 8192,
         "cpuarch" : "x86_64",
         "ip" : "172.16.64.2",
         "cluster" : "clusterb",
         "id" : 27,
         "virtual" : "ivt",
         "desktop_computing" : "NO",
         "opa_rate" : 0,
         "memnode" : 131072,
         "available_upto" : 2147483647,
         "opa_count" : 0,
         "ib_count" : 0,
         "expiry_date" : 0,
         "last_job_date" : 0,
         "myri_count" : 0,
         "cpufreq" : "2.1",
         "exotic" : "NO",
         "cpucore" : 8,
         "cpu" : 3,
         "deploy": "YES",
         "eth_rate" : 10,
         "drain" : "NO",
         "cpuset" : 7,
         "network_address" : "clusterb-2.fakesite.grid5000.fr",
         "suspended_jobs" : "NO"
      },
      {
         "next_finaud_decision" : "NO",
         "disk" : null,
         "cputype" : "Intel Xeon Silver 4110",
         "gpu_model" : "GeForce RTX 2080 Ti",
         "ib_rate" : 0,
         "gpu" : 7,
         "finaud_decision" : "NO",
         "memcpu" : 65536,
         "api_timestamp" : 1569497994,
         "gpu_count" : 4,
         "gpudevice" : 2,
         "last_available_upto" : 0,
         "wattmeter" : "MULTIPLE",
         "links" : [
            {
               "rel" : "member",
               "href" : "//oarapi/resources/nodes/clusterb-2.fakesite.grid5000.fr",
               "title" : "node"
            },
            {
               "rel" : "self",
               "href" : "//oarapi/resources/28"
            },
            {
               "title" : "jobs",
               "rel" : "collection",
               "href" : "//oarapi/resources/28/jobs"
            }
         ],
         "cluster_priority" : 201906,
         "maintenance" : "NO",
         "next_state" : "UnChanged",
         "host" : "clusterb-2.fakesite.grid5000.fr",
         "chassis" : "Dell Inc. PowerEdge T640 9L1CBX2",
         "nodemodel" : "Dell PowerEdge T640",
         "myri_rate" : 0,
         "eth_count" : 1,
         "ib" : "NO",
         "type" : "default",
         "state_num" : 1,
         "scheduler_priority" : 0,
         "state" : "Alive",
         "mic" : "NO",
         "disktype" : "SATA",
         "switch" : null,
         "diskpath" : null,
         "disk_reservation_count" : 3,
         "max_walltime" : 86400,
         "production" : "YES",
         "besteffort" : "YES",
         "myri" : "NO",
         "core" : 25,
         "available_upto" : 2147483647,
         "memnode" : 131072,
         "opa_rate" : 0,
         "id" : 28,
         "cluster" : "clusterb",
         "desktop_computing" : "NO",
         "virtual" : "ivt",
         "memcore" : 8192,
         "cpuarch" : "x86_64",
         "ip" : "172.16.64.2",
         "eth_rate" : 10,
         "drain" : "NO",
         "network_address" : "clusterb-2.fakesite.grid5000.fr",
         "suspended_jobs" : "NO",
         "cpuset" : 8,
         "ib_count" : 0,
         "expiry_date" : 0,
         "cpufreq" : "2.1",
         "exotic" : "NO",
         "myri_count" : 0,
         "cpucore" : 8,
         "cpu" : 4,
         "deploy": "YES",
         "last_job_date" : 0,
         "opa_count" : 0
      },
      {
         "besteffort" : "YES",
         "myri" : "NO",
         "core" : 26,
         "memnode" : 131072,
         "available_upto" : 2147483647,
         "opa_rate" : 0,
         "cluster" : "clusterb",
         "id" : 29,
         "desktop_computing" : "NO",
         "virtual" : "ivt",
         "memcore" : 8192,
         "cpuarch" : "x86_64",
         "ip" : "172.16.64.2",
         "drain" : "NO",
         "eth_rate" : 10,
         "network_address" : "clusterb-2.fakesite.grid5000.fr",
         "suspended_jobs" : "NO",
         "cpuset" : 9,
         "expiry_date" : 0,
         "ib_count" : 0,
         "myri_count" : 0,
         "cpufreq" : "2.1",
         "exotic" : "NO",
         "deploy": "YES",
         "cpucore" : 8,
         "cpu" : 4,
         "last_job_date" : 0,
         "opa_count" : 0,
         "disk" : null,
         "next_finaud_decision" : "NO",
         "cputype" : "Intel Xeon Silver 4110",
         "gpu_model" : "GeForce RTX 2080 Ti",
         "ib_rate" : 0,
         "finaud_decision" : "NO",
         "gpu" : 7,
         "memcpu" : 65536,
         "api_timestamp" : 1569497994,
         "gpu_count" : 4,
         "gpudevice" : 2,
         "last_available_upto" : 0,
         "wattmeter" : "MULTIPLE",
         "links" : [
            {
               "title" : "node",
               "rel" : "member",
               "href" : "//oarapi/resources/nodes/clusterb-2.fakesite.grid5000.fr"
            },
            {
               "rel" : "self",
               "href" : "//oarapi/resources/29"
            },
            {
               "rel" : "collection",
               "title" : "jobs",
               "href" : "//oarapi/resources/29/jobs"
            }
         ],
         "cluster_priority" : 201906,
         "maintenance" : "NO",
         "host" : "clusterb-2.fakesite.grid5000.fr",
         "chassis" : "Dell Inc. PowerEdge T640 9L1CBX2",
         "next_state" : "UnChanged",
         "nodemodel" : "Dell PowerEdge T640",
         "eth_count" : 1,
         "myri_rate" : 0,
         "ib" : "NO",
         "type" : "default",
         "state_num" : 1,
         "scheduler_priority" : 0,
         "state" : "Alive",
         "disktype" : "SATA",
         "mic" : "NO",
         "switch" : null,
         "diskpath" : null,
         "disk_reservation_count" : 3,
         "production" : "YES",
         "max_walltime" : 86400
      },
      {
         "gpu" : 7,
         "finaud_decision" : "NO",
         "cputype" : "Intel Xeon Silver 4110",
         "disk" : null,
         "next_finaud_decision" : "NO",
         "ib_rate" : 0,
         "gpu_model" : "GeForce RTX 2080 Ti",
         "last_available_upto" : 0,
         "wattmeter" : "MULTIPLE",
         "cluster_priority" : 201906,
         "links" : [
            {
               "rel" : "member",
               "title" : "node",
               "href" : "//oarapi/resources/nodes/clusterb-2.fakesite.grid5000.fr"
            },
            {
               "href" : "//oarapi/resources/30",
               "rel" : "self"
            },
            {
               "rel" : "collection",
               "href" : "//oarapi/resources/30/jobs",
               "title" : "jobs"
            }
         ],
         "maintenance" : "NO",
         "memcpu" : 65536,
         "api_timestamp" : 1569497994,
         "gpu_count" : 4,
         "gpudevice" : 2,
         "ib" : "NO",
         "type" : "default",
         "state_num" : 1,
         "next_state" : "UnChanged",
         "host" : "clusterb-2.fakesite.grid5000.fr",
         "chassis" : "Dell Inc. PowerEdge T640 9L1CBX2",
         "nodemodel" : "Dell PowerEdge T640",
         "eth_count" : 1,
         "myri_rate" : 0,
         "switch" : null,
         "diskpath" : null,
         "disk_reservation_count" : 3,
         "production" : "YES",
         "max_walltime" : 86400,
         "state" : "Alive",
         "scheduler_priority" : 0,
         "mic" : "NO",
         "disktype" : "SATA",
         "core" : 27,
         "myri" : "NO",
         "besteffort" : "YES",
         "id" : 30,
         "cluster" : "clusterb",
         "virtual" : "ivt",
         "desktop_computing" : "NO",
         "memcore" : 8192,
         "cpuarch" : "x86_64",
         "ip" : "172.16.64.2",
         "available_upto" : 2147483647,
         "memnode" : 131072,
         "opa_rate" : 0,
         "expiry_date" : 0,
         "ib_count" : 0,
         "cpucore" : 8,
         "myri_count" : 0,
         "cpufreq" : "2.1",
         "exotic" : "NO",
         "cpu" : 4,
         "last_job_date" : 0,
         "deploy": "YES",
         "opa_count" : 0,
         "eth_rate" : 10,
         "cpuset" : 10,
         "drain" : "NO",
         "network_address" : "clusterb-2.fakesite.grid5000.fr",
         "suspended_jobs" : "NO"
      },
      {
         "maintenance" : "NO",
         "links" : [
            {
               "href" : "//oarapi/resources/nodes/clusterb-2.fakesite.grid5000.fr",
               "rel" : "member",
               "title" : "node"
            },
            {
               "rel" : "self",
               "href" : "//oarapi/resources/31"
            },
            {
               "rel" : "collection",
               "href" : "//oarapi/resources/31/jobs",
               "title" : "jobs"
            }
         ],
         "cluster_priority" : 201906,
         "wattmeter" : "MULTIPLE",
         "last_available_upto" : 0,
         "gpudevice" : 2,
         "gpu_count" : 4,
         "api_timestamp" : 1569497994,
         "memcpu" : 65536,
         "finaud_decision" : "NO",
         "gpu" : 7,
         "ib_rate" : 0,
         "gpu_model" : "GeForce RTX 2080 Ti",
         "disk" : null,
         "cputype" : "Intel Xeon Silver 4110",
         "next_finaud_decision" : "NO",
         "production" : "YES",
         "max_walltime" : 86400,
         "disk_reservation_count" : 3,
         "diskpath" : null,
         "switch" : null,
         "mic" : "NO",
         "disktype" : "SATA",
         "state" : "Alive",
         "scheduler_priority" : 0,
         "state_num" : 1,
         "type" : "default",
         "ib" : "NO",
         "myri_rate" : 0,
         "eth_count" : 1,
         "host" : "clusterb-2.fakesite.grid5000.fr",
         "chassis" : "Dell Inc. PowerEdge T640 9L1CBX2",
         "next_state" : "UnChanged",
         "nodemodel" : "Dell PowerEdge T640",
         "core" : 28,
         "myri" : "NO",
         "besteffort" : "YES",
         "opa_count" : 0,
         "cpufreq" : "2.1",
         "exotic" : "NO",
         "myri_count" : 0,
         "cpu" : 4,
         "cpucore" : 8,
         "deploy": "YES",
         "last_job_date" : 0,
         "expiry_date" : 0,
         "ib_count" : 0,
         "eth_rate" : 10,
         "suspended_jobs" : "NO",
         "drain" : "NO",
         "network_address" : "clusterb-2.fakesite.grid5000.fr",
         "cpuset" : 11,
         "cpuarch" : "x86_64",
         "ip" : "172.16.64.2",
         "memcore" : 8192,
         "desktop_computing" : "NO",
         "virtual" : "ivt",
         "cluster" : "clusterb",
         "id" : 31,
         "opa_rate" : 0,
         "available_upto" : 2147483647,
         "memnode" : 131072
      },
      {
         "max_walltime" : 86400,
         "production" : "YES",
         "disk_reservation_count" : 3,
         "diskpath" : null,
         "switch" : null,
         "disktype" : "SATA",
         "mic" : "NO",
         "state" : "Alive",
         "scheduler_priority" : 0,
         "state_num" : 1,
         "type" : "default",
         "ib" : "NO",
         "myri_rate" : 0,
         "eth_count" : 1,
         "next_state" : "UnChanged",
         "host" : "clusterb-2.fakesite.grid5000.fr",
         "chassis" : "Dell Inc. PowerEdge T640 9L1CBX2",
         "nodemodel" : "Dell PowerEdge T640",
         "maintenance" : "NO",
         "links" : [
            {
               "href" : "//oarapi/resources/nodes/clusterb-2.fakesite.grid5000.fr",
               "rel" : "member",
               "title" : "node"
            },
            {
               "rel" : "self",
               "href" : "//oarapi/resources/32"
            },
            {
               "title" : "jobs",
               "rel" : "collection",
               "href" : "//oarapi/resources/32/jobs"
            }
         ],
         "cluster_priority" : 201906,
         "wattmeter" : "MULTIPLE",
         "last_available_upto" : 0,
         "gpudevice" : 3,
         "gpu_count" : 4,
         "api_timestamp" : 1569497994,
         "memcpu" : 65536,
         "gpu" : 8,
         "finaud_decision" : "NO",
         "ib_rate" : 0,
         "gpu_model" : "GeForce RTX 2080 Ti",
         "disk" : null,
         "next_finaud_decision" : "NO",
         "cputype" : "Intel Xeon Silver 4110",
         "opa_count" : 0,
         "cpu" : 4,
         "myri_count" : 0,
         "cpufreq" : "2.1",
         "exotic" : "NO",
         "cpucore" : 8,
         "last_job_date" : 0,
         "deploy": "YES",
         "expiry_date" : 0,
         "ib_count" : 0,
         "network_address" : "clusterb-2.fakesite.grid5000.fr",
         "eth_rate" : 10,
         "drain" : "NO",
         "cpuset" : 12,
         "suspended_jobs" : "NO",
         "cpuarch" : "x86_64",
         "ip" : "172.16.64.2",
         "memcore" : 8192,
         "virtual" : "ivt",
         "desktop_computing" : "NO",
         "cluster" : "clusterb",
         "id" : 32,
         "opa_rate" : 0,
         "available_upto" : 2147483647,
         "memnode" : 131072,
         "core" : 29,
         "myri" : "NO",
         "besteffort" : "YES"
      },
      {
         "finaud_decision" : "NO",
         "gpu" : 8,
         "gpu_model" : "GeForce RTX 2080 Ti",
         "ib_rate" : 0,
         "next_finaud_decision" : "NO",
         "disk" : null,
         "cputype" : "Intel Xeon Silver 4110",
         "links" : [
            {
               "href" : "//oarapi/resources/nodes/clusterb-2.fakesite.grid5000.fr",
               "rel" : "member",
               "title" : "node"
            },
            {
               "rel" : "self",
               "href" : "//oarapi/resources/33"
            },
            {
               "rel" : "collection",
               "title" : "jobs",
               "href" : "//oarapi/resources/33/jobs"
            }
         ],
         "cluster_priority" : 201906,
         "maintenance" : "NO",
         "last_available_upto" : 0,
         "wattmeter" : "MULTIPLE",
         "gpu_count" : 4,
         "gpudevice" : 3,
         "memcpu" : 65536,
         "api_timestamp" : 1569497994,
         "state_num" : 1,
         "ib" : "NO",
         "type" : "default",
         "nodemodel" : "Dell PowerEdge T640",
         "next_state" : "UnChanged",
         "host" : "clusterb-2.fakesite.grid5000.fr",
         "chassis" : "Dell Inc. PowerEdge T640 9L1CBX2",
         "eth_count" : 1,
         "myri_rate" : 0,
         "disk_reservation_count" : 3,
         "production" : "YES",
         "max_walltime" : 86400,
         "switch" : null,
         "diskpath" : null,
         "scheduler_priority" : 0,
         "state" : "Alive",
         "disktype" : "SATA",
         "mic" : "NO",
         "myri" : "NO",
         "core" : 30,
         "besteffort" : "YES",
         "memcore" : 8192,
         "cpuarch" : "x86_64",
         "ip" : "172.16.64.2",
         "cluster" : "clusterb",
         "id" : 33,
         "virtual" : "ivt",
         "desktop_computing" : "NO",
         "opa_rate" : 0,
         "available_upto" : 2147483647,
         "memnode" : 131072,
         "opa_count" : 0,
         "ib_count" : 0,
         "expiry_date" : 0,
         "myri_count" : 0,
         "cpucore" : 8,
         "cpufreq" : "2.1",
         "exotic" : "NO",
         "cpu" : 4,
         "deploy": "YES",
         "last_job_date" : 0,
         "cpuset" : 13,
         "eth_rate" : 10,
         "drain" : "NO",
         "network_address" : "clusterb-2.fakesite.grid5000.fr",
         "suspended_jobs" : "NO"
      },
      {
         "opa_rate" : 0,
         "available_upto" : 2147483647,
         "memnode" : 131072,
         "cpuarch" : "x86_64",
         "ip" : "172.16.64.2",
         "memcore" : 8192,
         "virtual" : "ivt",
         "desktop_computing" : "NO",
         "cluster" : "clusterb",
         "id" : 34,
         "eth_rate" : 10,
         "network_address" : "clusterb-2.fakesite.grid5000.fr",
         "drain" : "NO",
         "suspended_jobs" : "NO",
         "cpuset" : 14,
         "opa_count" : 0,
         "cpufreq" : "2.1",
         "exotic" : "NO",
         "myri_count" : 0,
         "last_job_date" : 0,
         "cpucore" : 8,
         "cpu" : 4,
         "deploy": "YES",
         "ib_count" : 0,
         "expiry_date" : 0,
         "besteffort" : "YES",
         "myri" : "NO",
         "core" : 31,
         "myri_rate" : 0,
         "eth_count" : 1,
         "next_state" : "UnChanged",
         "host" : "clusterb-2.fakesite.grid5000.fr",
         "chassis" : "Dell Inc. PowerEdge T640 9L1CBX2",
         "nodemodel" : "Dell PowerEdge T640",
         "state_num" : 1,
         "type" : "default",
         "ib" : "NO",
         "mic" : "NO",
         "disktype" : "SATA",
         "scheduler_priority" : 0,
         "state" : "Alive",
         "max_walltime" : 86400,
         "production" : "YES",
         "disk_reservation_count" : 3,
         "diskpath" : null,
         "switch" : null,
         "ib_rate" : 0,
         "gpu_model" : "GeForce RTX 2080 Ti",
         "disk" : null,
         "cputype" : "Intel Xeon Silver 4110",
         "next_finaud_decision" : "NO",
         "gpu" : 8,
         "finaud_decision" : "NO",
         "gpudevice" : 3,
         "gpu_count" : 4,
         "api_timestamp" : 1569497994,
         "memcpu" : 65536,
         "maintenance" : "NO",
         "cluster_priority" : 201906,
         "links" : [
            {
               "rel" : "member",
               "href" : "//oarapi/resources/nodes/clusterb-2.fakesite.grid5000.fr",
               "title" : "node"
            },
            {
               "href" : "//oarapi/resources/34",
               "rel" : "self"
            },
            {
               "rel" : "collection",
               "title" : "jobs",
               "href" : "//oarapi/resources/34/jobs"
            }
         ],
         "wattmeter" : "MULTIPLE",
         "last_available_upto" : 0
      },
      {
         "besteffort" : "YES",
         "core" : 32,
         "myri" : "NO",
         "available_upto" : 2147483647,
         "memnode" : 131072,
         "opa_rate" : 0,
         "desktop_computing" : "NO",
         "virtual" : "ivt",
         "id" : 35,
         "cluster" : "clusterb",
         "cpuarch" : "x86_64",
         "ip" : "172.16.64.2",
         "memcore" : 8192,
         "eth_rate" : 10,
         "suspended_jobs" : "NO",
         "drain" : "NO",
         "network_address" : "clusterb-2.fakesite.grid5000.fr",
         "cpuset" : 15,
         "myri_count" : 0,
         "cpufreq" : "2.1",
         "exotic" : "NO",
         "cpu" : 4,
         "cpucore" : 8,
         "last_job_date" : 0,
         "deploy": "YES",
         "expiry_date" : 0,
         "ib_count" : 0,
         "opa_count" : 0,
         "cputype" : "Intel Xeon Silver 4110",
         "disk" : null,
         "next_finaud_decision" : "NO",
         "ib_rate" : 0,
         "gpu_model" : "GeForce RTX 2080 Ti",
         "gpu" : 8,
         "finaud_decision" : "NO",
         "api_timestamp" : 1569497994,
         "memcpu" : 65536,
         "gpudevice" : 3,
         "gpu_count" : 4,
         "wattmeter" : "MULTIPLE",
         "last_available_upto" : 0,
         "maintenance" : "NO",
         "links" : [
            {
               "href" : "//oarapi/resources/nodes/clusterb-2.fakesite.grid5000.fr",
               "rel" : "member",
               "title" : "node"
            },
            {
               "href" : "//oarapi/resources/35",
               "rel" : "self"
            },
            {
               "rel" : "collection",
               "title" : "jobs",
               "href" : "//oarapi/resources/35/jobs"
            }
         ],
         "cluster_priority" : 201906,
         "eth_count" : 1,
         "myri_rate" : 0,
         "nodemodel" : "Dell PowerEdge T640",
         "next_state" : "UnChanged",
         "host" : "clusterb-2.fakesite.grid5000.fr",
         "chassis" : "Dell Inc. PowerEdge T640 9L1CBX2",
         "type" : "default",
         "ib" : "NO",
         "state_num" : 1,
         "mic" : "NO",
         "disktype" : "SATA",
         "scheduler_priority" : 0,
         "state" : "Alive",
         "diskpath" : null,
         "switch" : null,
         "production" : "YES",
         "max_walltime" : 86400,
         "disk_reservation_count" : 3
      },
      {
         "state_num" : 1,
         "type" : "disk",
         "ib" : "NO",
         "exotic" : "NO",
         "myri_rate" : 0,
         "eth_count" : 1,
         "next_state" : "UnChanged",
         "nodemodel" : "Dell PowerEdge T640",
         "host" : "clusterb-2.fakesite.grid5000.fr",
         "chassis" : "Dell Inc. PowerEdge T640 9L1CBX2",
         "max_walltime" : 0,
         "production" : "YES",
         "disk_reservation_count" : 3,
         "diskpath" : "/dev/disk/by-path/pci-0000:02:00.0-scsi-0:0:1:0",
         "switch" : null,
         "disktype" : "SATA",
         "mic" : "NO",
         "scheduler_priority" : 0,
         "state" : "Alive",
         "finaud_decision" : "NO",
         "gpu" : null,
         "gpu_model" : null,
         "ib_rate" : 0,
         "disk" : "sdb.clusterb-2",
         "cputype" : "Intel Xeon Silver 4110",
         "next_finaud_decision" : "NO",
         "maintenance" : "NO",
         "links" : [
            {
               "title" : "node",
               "rel" : "member",
               "href" : "//oarapi/resources/nodes/"
            },
            {
               "rel" : "self",
               "href" : "//oarapi/resources/36"
            },
            {
               "href" : "//oarapi/resources/36/jobs",
               "rel" : "collection",
               "title" : "jobs"
            }
         ],
         "cluster_priority" : 201906,
         "wattmeter" : "MULTIPLE",
         "last_available_upto" : 0,
         "gpudevice" : null,
         "gpu_count" : 4,
         "api_timestamp" : 1569497994,
         "memcpu" : 65536,
         "cpuarch" : "x86_64",
         "ip" : "172.16.64.2",
         "memcore" : 8192,
         "virtual" : "ivt",
         "desktop_computing" : "NO",
         "id" : 36,
         "cluster" : "clusterb",
         "opa_rate" : 0,
         "memnode" : 131072,
         "available_upto" : 0,
         "opa_count" : 0,
         "myri_count" : 0,
         "last_job_date" : 0,
         "cpufreq" : "2.1",
         "cpucore" : 8,
         "cpu" : null,
         "deploy" : "YES",
         "expiry_date" : 0,
         "ib_count" : 0,
         "suspended_jobs" : "NO",
         "eth_rate" : 10,
         "drain" : "NO",
         "network_address" : "",
         "cpuset" : -1,
         "myri" : "NO",
         "core" : null,
         "besteffort" : "YES"
      },
      {
         "besteffort" : "YES",
         "core" : null,
         "myri" : "NO",
         "eth_rate" : 10,
         "network_address" : "",
         "drain" : "NO",
         "cpuset" : -1,
         "suspended_jobs" : "NO",
         "ib_count" : 0,
         "expiry_date" : 0,
         "cpufreq" : "2.1",
         "myri_count" : 0,
         "cpucore" : 8,
         "cpu" : null,
         "last_job_date" : 0,
         "deploy" : "YES",
         "opa_count" : 0,
         "available_upto" : 0,
         "memnode" : 131072,
         "opa_rate" : 0,
         "id" : 37,
         "cluster" : "clusterb",
         "virtual" : "ivt",
         "desktop_computing" : "NO",
         "memcore" : 8192,
         "cpuarch" : "x86_64",
         "ip" : "172.16.64.2",
         "memcpu" : 65536,
         "api_timestamp" : 1569497994,
         "gpu_count" : 4,
         "gpudevice" : null,
         "last_available_upto" : 0,
         "wattmeter" : "MULTIPLE",
         "links" : [
            {
               "rel" : "member",
               "href" : "//oarapi/resources/nodes/",
               "title" : "node"
            },
            {
               "rel" : "self",
               "href" : "//oarapi/resources/37"
            },
            {
               "rel" : "collection",
               "title" : "jobs",
               "href" : "//oarapi/resources/37/jobs"
            }
         ],
         "cluster_priority" : 201906,
         "maintenance" : "NO",
         "disk" : "sdc.clusterb-2",
         "cputype" : "Intel Xeon Silver 4110",
         "next_finaud_decision" : "NO",
         "gpu_model" : null,
         "ib_rate" : 0,
         "finaud_decision" : "NO",
         "gpu" : null,
         "state" : "Alive",
         "scheduler_priority" : 0,
         "disktype" : "SATA",
         "mic" : "NO",
         "switch" : null,
         "diskpath" : "/dev/disk/by-path/pci-0000:02:00.0-scsi-0:0:2:0",
         "disk_reservation_count" : 3,
         "production" : "YES",
         "max_walltime" : 0,
         "next_state" : "UnChanged",
         "host" : "clusterb-2.fakesite.grid5000.fr",
         "chassis" : "Dell Inc. PowerEdge T640 9L1CBX2",
         "nodemodel" : "Dell PowerEdge T640",
         "myri_rate" : 0,
         "eth_count" : 1,
         "ib" : "NO",
         "exotic" : "NO",
         "type" : "disk",
         "state_num" : 1
      },
      {
         "gpu_model" : null,
         "ib_rate" : 0,
         "next_finaud_decision" : "NO",
         "disk" : "sdd.clusterb-2",
         "cputype" : "Intel Xeon Silver 4110",
         "gpu" : null,
         "finaud_decision" : "NO",
         "gpu_count" : 4,
         "gpudevice" : null,
         "memcpu" : 65536,
         "api_timestamp" : 1569497994,
         "cluster_priority" : 201906,
         "links" : [
            {
               "rel" : "member",
               "title" : "node",
               "href" : "//oarapi/resources/nodes/"
            },
            {
               "rel" : "self",
               "href" : "//oarapi/resources/38"
            },
            {
               "rel" : "collection",
               "title" : "jobs",
               "href" : "//oarapi/resources/38/jobs"
            }
         ],
         "maintenance" : "NO",
         "last_available_upto" : 0,
         "wattmeter" : "MULTIPLE",
         "nodemodel" : "Dell PowerEdge T640",
         "next_state" : "UnChanged",
         "host" : "clusterb-2.fakesite.grid5000.fr",
         "chassis" : "Dell Inc. PowerEdge T640 9L1CBX2",
         "eth_count" : 1,
         "myri_rate" : 0,
         "state_num" : 1,
         "ib" : "NO",
         "exotic" : "NO",
         "type" : "disk",
         "state" : "Alive",
         "scheduler_priority" : 0,
         "mic" : "NO",
         "disktype" : "SATA",
         "disk_reservation_count" : 3,
         "production" : "YES",
         "max_walltime" : 0,
         "switch" : null,
         "diskpath" : "/dev/disk/by-path/pci-0000:02:00.0-scsi-0:0:3:0",
         "besteffort" : "YES",
         "core" : null,
         "myri" : "NO",
         "opa_rate" : 0,
         "memnode" : 131072,
         "available_upto" : 0,
         "memcore" : 8192,
         "cpuarch" : "x86_64",
         "ip" : "172.16.64.2",
         "cluster" : "clusterb",
         "id" : 38,
         "virtual" : "ivt",
         "desktop_computing" : "NO",
         "network_address" : "",
         "eth_rate" : 10,
         "drain" : "NO",
         "suspended_jobs" : "NO",
         "cpuset" : -1,
         "opa_count" : 0,
         "expiry_date" : 0,
         "ib_count" : 0,
         "myri_count" : 0,
         "deploy" : "YES",
         "cpufreq" : "2.1",
         "cpucore" : 8,
         "cpu" : null,
         "last_job_date" : 0
      }
   ],
   "links" : [
      {
         "rel" : "self",
         "href" : "//oarapi/resources/details.json?limit=999999&offset=0"
      }
   ]
}

