{
  "architecture": {
    "platform_type": "x86_64",
    "smp_size": 2,
    "smt_size": 4
  },
  "main_memory": {
    "ram_size": 2147483648,
    "virtual_size": null
  },
  "network_adapters": [
    {
      "device": "eth0",
      "driver": "tg3",
      "enabled": true,
      "interface": "Ethernet",
      "ip": "172.28.54.119",
      "mac": "00:18:FE:FA:25:AE",
      "management": false,
      "mountable": true,
      "mounted": true,
      "network_address": "grelon-19.nancy.grid5000.fr",
      "rate": 1000000000,
      "switch": "sgrelon1",
      "switch_port": "19",
      "vendor": "Broadcom",
      "version": "BCM5721"
    },
    {
      "device": "eth1",
      "driver": "tg3",
      "enabled": true,
      "interface": "Ethernet",
      "ip": "172.28.55.119",
      "mac": "00:18:FE:FA:25:AF",
      "management": false,
      "mountable": true,
      "mounted": false,
      "rate": 1000000000,
      "switch": "sgrelon1",
      "switch_port": "43",
      "vendor": "Broadcom",
      "version": "BCM5721"
    },
    {
      "enabled": true,
      "interface": "Ethernet",
      "ip": "172.28.154.119",
      "mac": "00:18:FE:FA:32:99",
      "management": true,
      "mountable": false,
      "mounted": false,
      "network_address": "grelon-19-ipmi.nancy.grid5000.fr",
      "pdu": "pdu71",
      "pdu_port": "X4",
      "rate": 100000000,
      "switch": "sgrenade1",
      "switch_port": "19",
      "vendor": "hp_ilo",
      "version": "no"
    }
  ],
  "operating_system": {
    "name": null,
    "release": null,
    "version": null
  },
  "processor": {
    "cache_l1": null,
    "cache_l1d": null,
    "cache_l1i": null,
    "cache_l2": 4194304,
    "clock_speed": 1600000000.0,
    "instruction_set": "",
    "model": "Intel Xeon",
    "other_description": "",
    "vendor": "Intel",
    "version": "5110"
  },
  "serial": "GB8649YHPS",
  "storage_devices": [
    {
      "driver": "ata_piix",
      "interface": "SATA",
      "size": 74505805969.2383
    }
  ],
  "supported_job_types": {
    "besteffort": true,
    "deploy": true,
    "virtual": "ivt"
  },
  "type": "node",
  "uid": "grelon-19"
}