{
  "architecture": {
    "smp_size": 2,
    "smt_size": 8,
    "platform_type": "x86_64"
  },
  "processor": {
    "cache_l1": null,
    "model": "Intel Xeon",
    "cache_l1i": null,
    "vendor": "Intel",
    "cache_l1d": null,
    "clock_speed": 2500000000.0,
    "version": "E5420 QC",
    "cache_l2": null,
    "instruction_set": "",
    "other_description": ""
  },
  "storage_devices": [
    {
      "driver": null,
      "size": 149011611938.477,
      "interface": "SATA"
    }
  ],
  "main_memory": {
    "virtual_size": null,
    "ram_size": 8589934592
  },
  "type": "node",
  "uid": "genepi-30",
  "network_adapters": [

  ],
  "operating_system": {
    "version": null,
    "release": null,
    "name": null
  }
}