{
  "architecture": {
    "smp_size": 2,
    "smt_size": 4,
    "platform_type": "x86_64"
  },
  "processor": {
    "cache_l1": 1048576,
    "model": "AMD Opteron",
    "cache_l1i": null,
    "vendor": "AMD",
    "cache_l1d": null,
    "clock_speed": 2600000000.0,
    "version": "2218",
    "cache_l2": null,
    "instruction_set": "",
    "other_description": ""
  },
  "storage_devices": [
    {
      "driver": "sata_nv",
      "size": 232830643653.87,
      "interface": "SATA"
    }
  ],
  "main_memory": {
    "virtual_size": null,
    "ram_size": 8589934592
  },
  "type": "node",
  "uid": "pastel-42",
  "network_adapters": [
    {
      "driver": "forcedeth",
      "vendor": "NVIDIA",
      "rate": 1000000000,
      "version": "MCP55 Pro",
      "enabled": true,
      "interface": "Ethernet"
    },
    {
      "driver": "forcedeth",
      "vendor": "NVIDIA",
      "rate": 1000000000,
      "version": "MCP55 Pro",
      "enabled": false,
      "interface": "Ethernet"
    },
    {
      "driver": "tg3",
      "vendor": "Broadcom",
      "rate": 1000000000,
      "version": "BCM5715c",
      "enabled": false,
      "interface": "Ethernet"
    },
    {
      "driver": "tg3",
      "vendor": "Broadcom",
      "rate": 1000000000,
      "version": "BCM5715c",
      "enabled": false,
      "interface": "Ethernet"
    }
  ],
  "operating_system": {
    "version": null,
    "release": null,
    "name": null
  }
}