{
  "boot_type": "uefi",
  "created_at": "Fri, 25 Apr 2025 00:00:00 GMT",
  "exotic": false,
  "kavlan": true,
  "manufactured_at": "2025-04-03",
  "metrics": [
    {
      "description": "Temperature reported by BMC, in celsius",
      "name": "bmc_ambient_temp_celsius",
      "optional_period": 5000,
      "period": 0,
      "source": {
        "id": 2,
        "protocol": "ipmisensor"
      }
    },
    {
      "description": "Temperature of Cpu 1 Pkg reported by BMC, in celsius",
      "labels": {
        "cpu": "1pkg"
      },
      "name": "bmc_cpu_temp_celsius",
      "optional_period": 5000,
      "period": 0,
      "source": {
        "id": 3,
        "protocol": "ipmisensor"
      }
    },
    {
      "description": "Temperature of Dimm 1-8 reported by BMC, in celsius",
      "labels": {
        "dimm": "1-8"
      },
      "name": "bmc_dimm_temp_celsius",
      "optional_period": 5000,
      "period": 0,
      "source": {
        "id": 4,
        "protocol": "ipmisensor"
      }
    },
    {
      "description": "Temperature of Dimm 9-16 reported by BMC, in celsius",
      "labels": {
        "dimm": "9-16"
      },
      "name": "bmc_dimm_temp_celsius",
      "optional_period": 5000,
      "period": 0,
      "source": {
        "id": 6,
        "protocol": "ipmisensor"
      }
    },
    {
      "description": "Temperature of 12-VR P1 reported by BMC, in celsius",
      "labels": {
        "id": "12-vrp1"
      },
      "name": "bmc_other_temp_celsius",
      "optional_period": 5000,
      "period": 0,
      "source": {
        "id": 8,
        "protocol": "ipmisensor"
      }
    },
    {
      "description": "Temperature of 16-Exp Bay Drive reported by BMC, in celsius",
      "labels": {
        "id": "16-expbaydrive"
      },
      "name": "bmc_other_temp_celsius",
      "optional_period": 5000,
      "period": 0,
      "source": {
        "id": 11,
        "protocol": "ipmisensor"
      }
    },
    {
      "description": "Temperature of 21-Chipset reported by BMC, in celsius",
      "labels": {
        "id": "21-chipset"
      },
      "name": "bmc_other_temp_celsius",
      "optional_period": 5000,
      "period": 0,
      "source": {
        "id": 14,
        "protocol": "ipmisensor"
      }
    },
    {
      "description": "Temperature of 22-BMC reported by BMC, in celsius",
      "labels": {
        "id": "22-bmc"
      },
      "name": "bmc_other_temp_celsius",
      "optional_period": 5000,
      "period": 0,
      "source": {
        "id": 15,
        "protocol": "ipmisensor"
      }
    },
    {
      "description": "Temperature of 23-P/S 1 Inlet reported by BMC, in celsius",
      "labels": {
        "id": "23-p/s1inlet"
      },
      "name": "bmc_other_temp_celsius",
      "optional_period": 5000,
      "period": 0,
      "source": {
        "id": 16,
        "protocol": "ipmisensor"
      }
    },
    {
      "description": "Temperature of 24-P/S 1 reported by BMC, in celsius",
      "labels": {
        "id": "24-p/s1"
      },
      "name": "bmc_other_temp_celsius",
      "optional_period": 5000,
      "period": 0,
      "source": {
        "id": 17,
        "protocol": "ipmisensor"
      }
    },
    {
      "description": "Temperature of 25-P/S 2 Inlet reported by BMC, in celsius",
      "labels": {
        "id": "25-p/s2inlet"
      },
      "name": "bmc_other_temp_celsius",
      "optional_period": 5000,
      "period": 0,
      "source": {
        "id": 18,
        "protocol": "ipmisensor"
      }
    },
    {
      "description": "Temperature of 26-P/S 2 reported by BMC, in celsius",
      "labels": {
        "id": "26-p/s2"
      },
      "name": "bmc_other_temp_celsius",
      "optional_period": 5000,
      "period": 0,
      "source": {
        "id": 19,
        "protocol": "ipmisensor"
      }
    },
    {
      "description": "Temperature of 29-OCP 1 Zone reported by BMC, in celsius",
      "labels": {
        "id": "29-ocp1zone"
      },
      "name": "bmc_other_temp_celsius",
      "optional_period": 5000,
      "period": 0,
      "source": {
        "id": 20,
        "protocol": "ipmisensor"
      }
    },
    {
      "description": "Temperature of 36-Board Inlet reported by BMC, in celsius",
      "labels": {
        "id": "36-boardinlet"
      },
      "name": "bmc_other_temp_celsius",
      "optional_period": 5000,
      "period": 0,
      "source": {
        "id": 23,
        "protocol": "ipmisensor"
      }
    },
    {
      "description": "Temperature of 40-Battery Zone reported by BMC, in celsius",
      "labels": {
        "id": "40-batteryzone"
      },
      "name": "bmc_other_temp_celsius",
      "optional_period": 5000,
      "period": 0,
      "source": {
        "id": 24,
        "protocol": "ipmisensor"
      }
    },
    {
      "description": "Temperature of 41-P/S 1 Zone reported by BMC, in celsius",
      "labels": {
        "id": "41-p/s1zone"
      },
      "name": "bmc_other_temp_celsius",
      "optional_period": 5000,
      "period": 0,
      "source": {
        "id": 25,
        "protocol": "ipmisensor"
      }
    },
    {
      "description": "Temperature of 42-Sys Exhaust reported by BMC, in celsius",
      "labels": {
        "id": "42-sysexhaust"
      },
      "name": "bmc_other_temp_celsius",
      "optional_period": 5000,
      "period": 0,
      "source": {
        "id": 26,
        "protocol": "ipmisensor"
      }
    },
    {
      "description": "Usage of Fan 1 reported by BMC, in percent",
      "labels": {
        "fan": "1"
      },
      "name": "bmc_fan_usage_percent",
      "optional_period": 5000,
      "period": 0,
      "source": {
        "id": 34,
        "protocol": "ipmisensor"
      }
    },
    {
      "description": "Usage of Fan 2 reported by BMC, in percent",
      "labels": {
        "fan": "2"
      },
      "name": "bmc_fan_usage_percent",
      "optional_period": 5000,
      "period": 0,
      "source": {
        "id": 37,
        "protocol": "ipmisensor"
      }
    },
    {
      "description": "Usage of Fan 3 reported by BMC, in percent",
      "labels": {
        "fan": "3"
      },
      "name": "bmc_fan_usage_percent",
      "optional_period": 5000,
      "period": 0,
      "source": {
        "id": 40,
        "protocol": "ipmisensor"
      }
    },
    {
      "description": "Usage of Fan 4 reported by BMC, in percent",
      "labels": {
        "fan": "4"
      },
      "name": "bmc_fan_usage_percent",
      "optional_period": 5000,
      "period": 0,
      "source": {
        "id": 43,
        "protocol": "ipmisensor"
      }
    },
    {
      "description": "Usage of Fan 5 reported by BMC, in percent",
      "labels": {
        "fan": "5"
      },
      "name": "bmc_fan_usage_percent",
      "optional_period": 5000,
      "period": 0,
      "source": {
        "id": 46,
        "protocol": "ipmisensor"
      }
    },
    {
      "description": "Usage of Fan 6 reported by BMC, in percent",
      "labels": {
        "fan": "6"
      },
      "name": "bmc_fan_usage_percent",
      "optional_period": 5000,
      "period": 0,
      "source": {
        "id": 49,
        "protocol": "ipmisensor"
      }
    },
    {
      "description": "Usage of Fan 7 reported by BMC, in percent",
      "labels": {
        "fan": "7"
      },
      "name": "bmc_fan_usage_percent",
      "optional_period": 5000,
      "period": 0,
      "source": {
        "id": 52,
        "protocol": "ipmisensor"
      }
    },
    {
      "description": "Power consumption of Psu 1 reported by BMC, in watt",
      "labels": {
        "psu": "1"
      },
      "name": "bmc_psu_power_watt",
      "optional_period": 5000,
      "period": 0,
      "source": {
        "id": 55,
        "protocol": "ipmisensor"
      }
    },
    {
      "description": "Power consumption of Psu 2 reported by BMC, in watt",
      "labels": {
        "psu": "2"
      },
      "name": "bmc_psu_power_watt",
      "optional_period": 5000,
      "period": 0,
      "source": {
        "id": 57,
        "protocol": "ipmisensor"
      }
    },
    {
      "description": "Power consumption reported by BMC, in watt",
      "name": "bmc_node_power_watt",
      "optional_period": 5000,
      "period": 0,
      "source": {
        "id": 58,
        "protocol": "ipmisensor"
      }
    },
    {
      "description": "Power consumption of PS 1 Output reported by BMC, in watt",
      "labels": {
        "id": "ps1output"
      },
      "name": "bmc_other_power_watt",
      "optional_period": 5000,
      "period": 0,
      "source": {
        "id": 67,
        "protocol": "ipmisensor"
      }
    },
    {
      "description": "Voltage of PS_Volt_Out_01 reported by BMC, in volt",
      "labels": {
        "id": "ps_volt_out_01"
      },
      "name": "bmc_other_voltage_volt",
      "optional_period": 5000,
      "period": 0,
      "source": {
        "id": 68,
        "protocol": "ipmisensor"
      }
    },
    {
      "description": "Voltage of PS_Volt_In_01 reported by BMC, in volt",
      "labels": {
        "id": "ps_volt_in_01"
      },
      "name": "bmc_other_voltage_volt",
      "optional_period": 5000,
      "period": 0,
      "source": {
        "id": 69,
        "protocol": "ipmisensor"
      }
    },
    {
      "description": "Current of PS_Curr_Out_01 reported by BMC, in amp",
      "labels": {
        "id": "ps_curr_out_01"
      },
      "name": "bmc_other_current_amp",
      "optional_period": 5000,
      "period": 0,
      "source": {
        "id": 70,
        "protocol": "ipmisensor"
      }
    },
    {
      "description": "Current of PS_Curr_In_01 reported by BMC, in amp",
      "labels": {
        "id": "ps_curr_in_01"
      },
      "name": "bmc_other_current_amp",
      "optional_period": 5000,
      "period": 0,
      "source": {
        "id": 71,
        "protocol": "ipmisensor"
      }
    },
    {
      "description": "Power consumption of PS 2 Output reported by BMC, in watt",
      "labels": {
        "id": "ps2output"
      },
      "name": "bmc_other_power_watt",
      "optional_period": 5000,
      "period": 0,
      "source": {
        "id": 72,
        "protocol": "ipmisensor"
      }
    },
    {
      "description": "Voltage of PS_Volt_Out_02 reported by BMC, in volt",
      "labels": {
        "id": "ps_volt_out_02"
      },
      "name": "bmc_other_voltage_volt",
      "optional_period": 5000,
      "period": 0,
      "source": {
        "id": 73,
        "protocol": "ipmisensor"
      }
    },
    {
      "description": "Voltage of PS_Volt_In_02 reported by BMC, in volt",
      "labels": {
        "id": "ps_volt_in_02"
      },
      "name": "bmc_other_voltage_volt",
      "optional_period": 5000,
      "period": 0,
      "source": {
        "id": 74,
        "protocol": "ipmisensor"
      }
    },
    {
      "description": "Current of PS_Curr_Out_02 reported by BMC, in amp",
      "labels": {
        "id": "ps_curr_out_02"
      },
      "name": "bmc_other_current_amp",
      "optional_period": 5000,
      "period": 0,
      "source": {
        "id": 75,
        "protocol": "ipmisensor"
      }
    },
    {
      "description": "Current of PS_Curr_In_02 reported by BMC, in amp",
      "labels": {
        "id": "ps_curr_in_02"
      },
      "name": "bmc_other_current_amp",
      "optional_period": 5000,
      "period": 0,
      "source": {
        "id": 76,
        "protocol": "ipmisensor"
      }
    },
    {
      "description": "Temperature of 50.1-XLR8R 4-GPU reported by BMC, in celsius",
      "labels": {
        "id": "50.1-xlr8r4-gpu"
      },
      "name": "bmc_other_temp_celsius",
      "optional_period": 5000,
      "period": 0,
      "source": {
        "id": 77,
        "protocol": "ipmisensor"
      }
    },
    {
      "description": "Temperature of 28.1-OCP 1-Netwo reported by BMC, in celsius",
      "labels": {
        "id": "28.1-ocp1-netwo"
      },
      "name": "bmc_other_temp_celsius",
      "optional_period": 5000,
      "period": 0,
      "source": {
        "id": 78,
        "protocol": "ipmisensor"
      }
    },
    {
      "description": "Default subset of metrics from Prometheus Node Exporter",
      "name": "prom_default_metrics",
      "optional_period": 15000,
      "period": 0,
      "source": {
        "id": [
          "node_boot_time_seconds",
          "node_cpu_scaling_frequency_hertz",
          "node_cpu_seconds_total",
          "node_filesystem_free_bytes",
          "node_filesystem_size_bytes",
          "node_load1",
          "node_load15",
          "node_load5",
          "node_memory_Buffers_bytes",
          "node_memory_Cached_bytes",
          "node_memory_MemAvailable_bytes",
          "node_memory_MemFree_bytes",
          "node_memory_MemTotal_bytes",
          "node_memory_Shmem_bytes",
          "node_memory_SwapFree_bytes",
          "node_memory_SwapTotal_bytes",
          "node_network_receive_bytes_total",
          "node_network_receive_packets_total",
          "node_network_transmit_bytes_total",
          "node_network_transmit_packets_total",
          "node_procs_blocked",
          "node_procs_running",
          "kwollect_custom"
        ],
        "port": 9100,
        "protocol": "prometheus"
      }
    },
    {
      "description": "All metrics from Prometheus Node Exporter",
      "name": "prom_all_metrics",
      "optional_period": 15000,
      "period": 0,
      "source": {
        "port": 9100,
        "protocol": "prometheus"
      }
    },
    {
      "description": "Default subset of metrics from Prometheus Nvidia DCGM Exporter",
      "name": "prom_nvgpu_default_metrics",
      "optional_period": 15000,
      "period": 0,
      "source": {
        "id": [
          "DCGM_FI_DEV_SM_CLOCK",
          "DCGM_FI_DEV_MEM_CLOCK",
          "DCGM_FI_DEV_GPU_TEMP",
          "DCGM_FI_DEV_POWER_USAGE",
          "DCGM_FI_DEV_MEM_COPY_UTIL"
        ],
        "port": 9400,
        "protocol": "prometheus"
      }
    },
    {
      "description": "All metrics from Prometheus Nvidia DCGM Exporter",
      "name": "prom_nvgpu_all_metrics",
      "optional_period": 15000,
      "period": 0,
      "source": {
        "port": 9400,
        "protocol": "prometheus"
      }
    },
    {
      "description": "Input byte counter for the network device port",
      "labels": {
        "interface": "eth0"
      },
      "name": "network_ifacein_bytes_total",
      "period": 10000,
      "source": {
        "protocol": "network_equipment"
      }
    },
    {
      "description": "Output byte counter for the network device port",
      "labels": {
        "interface": "eth0"
      },
      "name": "network_ifaceout_bytes_total",
      "period": 10000,
      "source": {
        "protocol": "network_equipment"
      }
    },
    {
      "description": "Input packet counter for the network device port",
      "labels": {
        "interface": "eth0"
      },
      "name": "network_ifacein_packets_total",
      "period": 10000,
      "source": {
        "protocol": "network_equipment"
      }
    },
    {
      "description": "Output packet counter for the network device port",
      "labels": {
        "interface": "eth0"
      },
      "name": "network_ifaceout_packets_total",
      "period": 10000,
      "source": {
        "protocol": "network_equipment"
      }
    },
    {
      "description": "Input counter of discarded packets for the network device port",
      "labels": {
        "interface": "eth0"
      },
      "name": "network_ifacein_packets_discard_total",
      "period": 10000,
      "source": {
        "protocol": "network_equipment"
      }
    },
    {
      "description": "Output counter of discarded packets for the network device port",
      "labels": {
        "interface": "eth0"
      },
      "name": "network_ifaceout_packets_discard_total",
      "period": 10000,
      "source": {
        "protocol": "network_equipment"
      }
    },
    {
      "description": "Input counter of packet errors for the network device port",
      "labels": {
        "interface": "eth0"
      },
      "name": "network_ifacein_packets_error_total",
      "period": 10000,
      "source": {
        "protocol": "network_equipment"
      }
    },
    {
      "description": "Output counter of packet errors for the network device port",
      "labels": {
        "interface": "eth0"
      },
      "name": "network_ifaceout_packets_error_total",
      "period": 10000,
      "source": {
        "protocol": "network_equipment"
      }
    },
    {
      "description": "Input byte counter for the network device port",
      "labels": {
        "interface": "eth1"
      },
      "name": "network_ifacein_bytes_total",
      "period": 10000,
      "source": {
        "protocol": "network_equipment"
      }
    },
    {
      "description": "Output byte counter for the network device port",
      "labels": {
        "interface": "eth1"
      },
      "name": "network_ifaceout_bytes_total",
      "period": 10000,
      "source": {
        "protocol": "network_equipment"
      }
    },
    {
      "description": "Input packet counter for the network device port",
      "labels": {
        "interface": "eth1"
      },
      "name": "network_ifacein_packets_total",
      "period": 10000,
      "source": {
        "protocol": "network_equipment"
      }
    },
    {
      "description": "Output packet counter for the network device port",
      "labels": {
        "interface": "eth1"
      },
      "name": "network_ifaceout_packets_total",
      "period": 10000,
      "source": {
        "protocol": "network_equipment"
      }
    },
    {
      "description": "Input counter of discarded packets for the network device port",
      "labels": {
        "interface": "eth1"
      },
      "name": "network_ifacein_packets_discard_total",
      "period": 10000,
      "source": {
        "protocol": "network_equipment"
      }
    },
    {
      "description": "Output counter of discarded packets for the network device port",
      "labels": {
        "interface": "eth1"
      },
      "name": "network_ifaceout_packets_discard_total",
      "period": 10000,
      "source": {
        "protocol": "network_equipment"
      }
    },
    {
      "description": "Input counter of packet errors for the network device port",
      "labels": {
        "interface": "eth1"
      },
      "name": "network_ifacein_packets_error_total",
      "period": 10000,
      "source": {
        "protocol": "network_equipment"
      }
    },
    {
      "description": "Output counter of packet errors for the network device port",
      "labels": {
        "interface": "eth1"
      },
      "name": "network_ifaceout_packets_error_total",
      "period": 10000,
      "source": {
        "protocol": "network_equipment"
      }
    }
  ],
  "model": "ProLiant DL320 Gen11",
  "nodes_count": 1,
  "nodes_description": "1 CPU Intel Xeon Gold 5420+, 28 cores/CPU, 1 GPU L40S, 128GB RAM, 745GB SSD, 2 x 25Gb Ethernet",
  "priority": 202604,
  "queues": [
    "abaca",
    "admin",
    "production"
  ],
  "redfish": true,
  "type": "cluster",
  "uid": "chiconade1",
  "warranty_end": "2028-04-09"
}