{
  "created_at": "Fri, 21 Feb 2014 00:00:00 GMT",
  "exotic": false,
  "kavlan": true,
  "metrics": [
    {
      "description": "Default subset of metrics from Prometheus Node Exporter",
      "name": "prom_default_metrics",
      "optional_period": 15000,
      "period": 0,
      "source": {
        "id": [
          "node_boot_time_seconds",
          "node_cpu_frequency_hertz",
          "node_cpu_seconds_total",
          "node_filesystem_free_bytes",
          "node_filesystem_size_bytes",
          "node_load1",
          "node_load15",
          "node_load5",
          "node_memory_Buffers_bytes",
          "node_memory_Cached_bytes",
          "node_memory_MemAvailable_bytes",
          "node_memory_MemFree_bytes",
          "node_memory_MemTotal_bytes",
          "node_memory_Shmem_bytes",
          "node_memory_SwapFree_bytes",
          "node_memory_SwapTotal_bytes",
          "node_network_receive_bytes_total",
          "node_network_receive_packets_total",
          "node_network_transmit_bytes_total",
          "node_network_transmit_packets_total",
          "node_procs_blocked",
          "node_procs_running",
          "kwollect_custom"
        ],
        "port": 9100,
        "protocol": "prometheus"
      }
    },
    {
      "description": "All metrics from Prometheus Node Exporter",
      "name": "prom_all_metrics",
      "optional_period": 15000,
      "period": 0,
      "source": {
        "port": 9100,
        "protocol": "prometheus"
      }
    },
    {
      "description": "Input byte counter for the network device port",
      "labels": {
        "interface": "eth0"
      },
      "name": "network_ifacein_bytes_total",
      "period": 15000,
      "source": {
        "protocol": "network_equipment"
      }
    },
    {
      "description": "Output byte counter for the network device port",
      "labels": {
        "interface": "eth0"
      },
      "name": "network_ifaceout_bytes_total",
      "period": 15000,
      "source": {
        "protocol": "network_equipment"
      }
    },
    {
      "description": "Input packet counter for the network device port",
      "labels": {
        "interface": "eth0"
      },
      "name": "network_ifacein_packets_total",
      "period": 15000,
      "source": {
        "protocol": "network_equipment"
      }
    },
    {
      "description": "Output packet counter for the network device port",
      "labels": {
        "interface": "eth0"
      },
      "name": "network_ifaceout_packets_total",
      "period": 15000,
      "source": {
        "protocol": "network_equipment"
      }
    },
    {
      "description": "Input counter of discarded packets for the network device port",
      "labels": {
        "interface": "eth0"
      },
      "name": "network_ifacein_packets_discard_total",
      "period": 15000,
      "source": {
        "protocol": "network_equipment"
      }
    },
    {
      "description": "Output counter of discarded packets for the network device port",
      "labels": {
        "interface": "eth0"
      },
      "name": "network_ifaceout_packets_discard_total",
      "period": 15000,
      "source": {
        "protocol": "network_equipment"
      }
    },
    {
      "description": "Input counter of packet errors for the network device port",
      "labels": {
        "interface": "eth0"
      },
      "name": "network_ifacein_packets_error_total",
      "period": 15000,
      "source": {
        "protocol": "network_equipment"
      }
    },
    {
      "description": "Output counter of packet errors for the network device port",
      "labels": {
        "interface": "eth0"
      },
      "name": "network_ifaceout_packets_error_total",
      "period": 15000,
      "source": {
        "protocol": "network_equipment"
      }
    },
    {
      "description": "Input byte counter for the network device port",
      "labels": {
        "interface": "eth1"
      },
      "name": "network_ifacein_bytes_total",
      "period": 15000,
      "source": {
        "protocol": "network_equipment"
      }
    },
    {
      "description": "Output byte counter for the network device port",
      "labels": {
        "interface": "eth1"
      },
      "name": "network_ifaceout_bytes_total",
      "period": 15000,
      "source": {
        "protocol": "network_equipment"
      }
    },
    {
      "description": "Input packet counter for the network device port",
      "labels": {
        "interface": "eth1"
      },
      "name": "network_ifacein_packets_total",
      "period": 15000,
      "source": {
        "protocol": "network_equipment"
      }
    },
    {
      "description": "Output packet counter for the network device port",
      "labels": {
        "interface": "eth1"
      },
      "name": "network_ifaceout_packets_total",
      "period": 15000,
      "source": {
        "protocol": "network_equipment"
      }
    },
    {
      "description": "Input counter of discarded packets for the network device port",
      "labels": {
        "interface": "eth1"
      },
      "name": "network_ifacein_packets_discard_total",
      "period": 15000,
      "source": {
        "protocol": "network_equipment"
      }
    },
    {
      "description": "Output counter of discarded packets for the network device port",
      "labels": {
        "interface": "eth1"
      },
      "name": "network_ifaceout_packets_discard_total",
      "period": 15000,
      "source": {
        "protocol": "network_equipment"
      }
    },
    {
      "description": "Input counter of packet errors for the network device port",
      "labels": {
        "interface": "eth1"
      },
      "name": "network_ifacein_packets_error_total",
      "period": 15000,
      "source": {
        "protocol": "network_equipment"
      }
    },
    {
      "description": "Output counter of packet errors for the network device port",
      "labels": {
        "interface": "eth1"
      },
      "name": "network_ifaceout_packets_error_total",
      "period": 15000,
      "source": {
        "protocol": "network_equipment"
      }
    },
    {
      "description": "Input byte counter for the network device port",
      "labels": {
        "interface": "eth2"
      },
      "name": "network_ifacein_bytes_total",
      "period": 10000,
      "source": {
        "protocol": "network_equipment"
      }
    },
    {
      "description": "Output byte counter for the network device port",
      "labels": {
        "interface": "eth2"
      },
      "name": "network_ifaceout_bytes_total",
      "period": 10000,
      "source": {
        "protocol": "network_equipment"
      }
    },
    {
      "description": "Input packet counter for the network device port",
      "labels": {
        "interface": "eth2"
      },
      "name": "network_ifacein_packets_total",
      "period": 10000,
      "source": {
        "protocol": "network_equipment"
      }
    },
    {
      "description": "Output packet counter for the network device port",
      "labels": {
        "interface": "eth2"
      },
      "name": "network_ifaceout_packets_total",
      "period": 10000,
      "source": {
        "protocol": "network_equipment"
      }
    },
    {
      "description": "Input counter of discarded packets for the network device port",
      "labels": {
        "interface": "eth2"
      },
      "name": "network_ifacein_packets_discard_total",
      "period": 10000,
      "source": {
        "protocol": "network_equipment"
      }
    },
    {
      "description": "Output counter of discarded packets for the network device port",
      "labels": {
        "interface": "eth2"
      },
      "name": "network_ifaceout_packets_discard_total",
      "period": 10000,
      "source": {
        "protocol": "network_equipment"
      }
    },
    {
      "description": "Input counter of packet errors for the network device port",
      "labels": {
        "interface": "eth2"
      },
      "name": "network_ifacein_packets_error_total",
      "period": 10000,
      "source": {
        "protocol": "network_equipment"
      }
    },
    {
      "description": "Output counter of packet errors for the network device port",
      "labels": {
        "interface": "eth2"
      },
      "name": "network_ifaceout_packets_error_total",
      "period": 10000,
      "source": {
        "protocol": "network_equipment"
      }
    }
  ],
  "model": "Dell PowerEdge C6220 II",
  "queues": [
    "default",
    "admin"
  ],
  "sriov": false,
  "type": "cluster",
  "uid": "paranoia"
}