{
  "kind": "router",
  "linecards": [
    {

    },
    {
      "ports": [
        {

        },
        {

        },
        {

        },
        {
          "kind": "switch",
          "rate": 10000000000,
          "uid": "sgraphene3"
        },
        {
          "kind": "switch",
          "rate": 10000000000,
          "uid": "sgriffon2"
        }
      ]
    },
    {
      "ports": [
        {

        },
        {
          "kind": "switch",
          "rate": 10000000000,
          "uid": "sgraphene1"
        },
        {
          "kind": "switch",
          "rate": 10000000000,
          "uid": "sgraphene2"
        },
        {

        },
        {
          "kind": "switch",
          "rate": 10000000000,
          "uid": "sgraphene4"
        }
      ]
    },
    {
      "ports": [
        {

        },
        {

        },
        {

        },
        {
          "kind": "switch",
          "rate": 10000000000,
          "uid": "sgriffon3"
        },
        {
          "kind": "switch",
          "rate": 10000000000,
          "uid": "sgriffon1"
        }
      ]
    }
  ],
  "mac": "00:18:71:d7:e9:00",
  "model": "HP Procurve 5406zl",
  "networks": [
    {
      "cidr": "172.16.64.0/20",
      "kind": "default"
    },
    {
      "cidr": "10.144.0.0/14",
      "kind": "virtual"
    }
  ],
  "trunks": [

  ],
  "type": "network_equipment",
  "uid": "gw"
}