{
  "ip": "172.17.79.253",
  "kind": "hpcswitch",
  "linecards": [
    {
    },
    {
      "kavlan_pattern": "%LINECARD%/%PORT%",
      "kind": "switch",
      "ports": [

      ],
      "rate": 100000000000,
      "snmp_pattern": "%LINECARD%/%PORT%"
    }
  ],
  "managed_by_us": true,
  "model": "Omni-Path",
  "pdu": [
    {
      "port": 10,
      "uid": "grimani-pdu1"
    },
    {
      "port": 10,
      "uid": "grimani-pdu2"
    }
  ],
  "site": "nancy",
  "snmp_community": "public",
  "type": "network_equipment",
  "uid": "sgrele-opf",
  "warranty": "2022-06-01"
}